{"baseBpm":300,"musics":[{"id":1,"bpm":300,"baseBeats":0.5,"scores":["7<a[M],b[M],#c1[M],#d1[M]>,7<a[M],b[M],#c1[M],#d1[M]>,7<a[M],b[M],#c1[M],#d1[M]>,7<a[M],b[M],#c1[M],#d1[M]>,7<a[M],b[M],#c1[M],#d1[M]>,7<a[M],b[M],#c1[M],#d1[M]>,7<a[M],b[M],#c1[M],#d1[M]>,7<a[M],b[M],#c1[M],#d1[M]>,3<#A-1[N],#A-1[N],#A-1[N],#A-1[N],#A-1[N],#A-1[N],#A-1[N],#A-1[N],#A-1[N],#A-1[N],#A-1[N],#A-1[N],#A-1[N],#A-1[N],#A-1[N],#A-1[N],#A-1[N],#A-1[N],#A-1[N],#A-1[N],#A-1[N],#A-1[N],#A-1[N],#A-1[N],#A-1[N],#A-1[N],#A-1[N],#A-1[N],#A-1[N],#A-1[N],#A-1[N],#A-1[N],#A-1[N],#A-1[N],#A-1[N],#A-1[N],#A-1[N],#A-1[N],#A-1[N],#A-1[N],#A-1[N],#A-1[N],#A-1[N],#A-1[N],#A-1[N],#A-1[N],#A-1[N],#A-1[N],#A-1[N],#A-1[N],#A-1[N],#A-1[N],#A-1[N],#A-1[N],#A-1[N],#A-1[N],#A-1[N],#A-1[N],#A-1[N],#A-1[N],#A-1[N],#A-1[N],#A-1[N],#A-1[N],#A-1[N],#A-1[N],#A-1[N],#A-1[N],#A-1[N],#A-1[N],#A-1[N],#A-1[N],#A-1[N],#A-1[N],#A-1[N],#A-1[N],#A-1[N],#A-1[N],#A-1[N],#A-1[N],#A-1[N],#A-1[N],#A-1[N],#A-1[N],#A-1[N],#A-1[N],#A-1[N],#A-1[N],#A-1[N],#A-1[N],#A-1[N],#A-1[N],#A-1[N],#A-1[N],#A-1[N],#A-1[N],#A-1[N],#A-1[N],#A-1[N],#A-1[N],#A-1[N],#A-1[N],#A-1[N],#A-1[N],#A-1[N],#A-1[N],#A-1[N],#A-1[N],#A-1[N],#A-1[N],#A-1[N],#A-1[N],#A-1[N],#A-1[N],#A-1[N],#A-1[N],#A-1[N],#A-1[N],#A-1[N],#A-1[N],#A-1[N],#A-1[N],#A-1[N],#A-1[N],#A-1[N],#A-1[N],#A-1[N],#A-1[N],#A-1[N],#A-1[N],#A-1[N],#A-1[N],#A-1[N],#A-1[N],#A-1[N],#A-1[N],#A-1[N],#A-1[N],#A-1[N],#A-1[N],#A-1[N],#A-1[N],#A-1[N],#A-1[N],#A-1[N],#A-1[N],#A-1[N],#A-1[N],#A-1[N],#A-1[N],#A-1[N],#A-1[N],#A-1[N],#A-1[N],#A-1[N],#A-1[N],#A-1[N],#A-1[N],#A-1[N],#A-1[N],#A-1[N],#A-1[N],#A-1[N],#A-1[N],#A-1[N],#A-1[N],#A-1[N],#A-1[N],#A-1[N],#A-1[N],#A-1[N],#A-1[N],#A-1[N],#A-1[N],#A-1[N],#A-1[N],#A-1[N],#A-1[N],#A-1[N],#A-1[N],#A-1[N],#A-1[N],#A-1[N],#A-1[N],#A-1[N],#A-1[N],#A-1[N],#A-1[N],#A-1[N],#A-1[N],#A-1[N],#A-1[N],#A-1[N],#A-1[N],#A-1[N],#A-1[N],#A-1[N],#A-1[N],#A-1[N],#A-1[N],#A-1[N],#A-1[N],#A-1[N],#A-1[N],#A-1[N],#A-1[N],#A-1[N],#A-1[N],#A-1[N],#A-1[N],#A-1[N],#A-1[N],#A-1[N],#A-1[N],#A-1[N],#A-1[N],#A-1[N],#A-1[N],#A-1[N],#A-1[N],#A-1[N],#A-1[N],#A-1[N],#A-1[N],#A-1[N],#A-1[N],#A-1[N],#A-1[N],#A-1[N],#A-1[N],#A-1[N],#A-1[N],#A-1[N],#A-1[N],#A-1[N],#A-1[N],#A-1[N],#A-1[N],#A-1[N],#A-1[N],#A-1[N],#A-1[N],#A-1[N],#A-1[N],#A-1[N],#A-1[N],#A-1[N],#A-1[N],#A-1[N],#A-1[N],#A-1[N],#A-1[N],#A-1[N],#A-1[N],#A-1[N],#A-1[N]>,3<c[N],c[N],c[N],c[N],c[N],c[N],c[N],c[N],c[N],c[N],c[N],c[N],c[N],c[N],c[N],c[N],c[N],c[N],c[N],c[N],c[N],c[N],c[N],c[N],c[N],c[N],c[N],c[N],c[N],c[N],c[N],c[N],c[N],c[N],c[N],c[N],c[N],c[N],c[N],c[N],c[N],c[N],c[N],c[N],c[N],c[N],c[N],c[N],c[N],c[N],c[N],c[N],c[N],c[N],c[N],c[N],c[N],c[N],c[N],c[N],c[N],c[N],c[N],c[N],c[N],c[N],c[N],c[N],c[N],c[N],c[N],c[N],c[N],c[N],c[N],c[N],c[N],c[N],c[N],c[N],c[N],c[N],c[N],c[N],c[N],c[N],c[N],c[N],c[N],c[N],c[N],c[N],c[N],c[N],c[N],c[N],c[N],c[N],c[N],c[N],c[N],c[N],c[N],c[N],c[N],c[N],c[N],c[N],c[N],c[N],c[N],c[N],c[N],c[N],c[N],c[N],c[N],c[N],c[N],c[N],c[N],c[N],c[N],c[N],c[N],c[N],c[N],c[N],c[N],c[N],c[N],c[N],c[N],c[N],c[N],c[N],c[N],c[N],c[N],c[N],c[N],c[N],c[N],c[N],c[N],c[N],c[N],c[N],c[N],c[N],c[N],c[N],c[N],c[N],c[N],c[N],c[N],c[N],c[N],c[N],c[N],c[N],c[N],c[N],c[N],c[N],c[N],c[N],c[N],c[N],c[N],c[N],c[N],c[N],c[N],c[N],c[N],c[N],c[N],c[N],c[N],c[N],c[N],c[N],c[N],c[N],c[N],c[N],c[N],c[N],c[N],c[N],c[N],c[N],c[N],c[N],c[N],c[N],c[N],c[N],c[N],c[N],c[N],c[N],c[N],c[N],c[N],c[N],c[N],c[N],c[N],c[N],c[N],c[N],c[N],c[N],c[N],c[N],c[N],c[N],c[N],c[N],c[N],c[N],c[N],c[N],c[N],c[N],c[N],c[N],c[N],c[N],c[N],c[N],c[N],c[N],c[N],c[N],c[N],c[N],c[N],c[N],c[N],c[N],c[N],c[N],c[N],c[N],c[N],c[N],c[N],c[N],c[N],c[N],c[N],c[N]>,6<#A-1[N],#A-1[N],#A-1[N],#A-1[N],c[N],c[N],c[N],c[N],#A-1[N],#A-1[N],#A-1[N],c[N],c[N],c[N],c[N]>,(A-1.#c.e.a)[H];"]},{"id":2,"bpm":330,"baseBeats":0.5,"scores":["e[L],e[L],e[L],e[L],d[L],d[L],d[L],d[L],e[L],e[L],e[L],e[L],d[L],d[L],d[L],d[L],e[L],e[L],e[L],e[L],d[L],d[L],d[L],d[L],e[L],e[L],e[L],e[L],d[L],d[L],d[L],d[L],e[L],e[L],e[L],e[L],d[L],d[L],d[L],d[L],e[L],e[L],e[L],e[L],d[L],d[L],d[L],d[L],e[L],e[L],e[L],e[L],d[L],d[L],d[L],d[L],e[L],e[L],e[L],e[L],d[L],d[L],d[L],d[L],3<#A-1[N],#A-1[N],#A-1[N],#A-1[N],#A-1[N],#A-1[N],#A-1[N],#A-1[N],#A-1[N],#A-1[N],#A-1[N],#A-1[N],#A-1[N],#A-1[N],#A-1[N],#A-1[N],#A-1[N],#A-1[N],#A-1[N],#A-1[N],#A-1[N],#A-1[N],#A-1[N],#A-1[N],#A-1[N],#A-1[N],#A-1[N],#A-1[N],#A-1[N],#A-1[N],#A-1[N],#A-1[N],#A-1[N],#A-1[N],#A-1[N],#A-1[N],#A-1[N],#A-1[N],#A-1[N],#A-1[N],#A-1[N],#A-1[N],#A-1[N],#A-1[N],#A-1[N],#A-1[N],#A-1[N],#A-1[N],#A-1[N],#A-1[N],#A-1[N],#A-1[N],#A-1[N],#A-1[N],#A-1[N],#A-1[N],#A-1[N],#A-1[N],#A-1[N],#A-1[N],#A-1[N],#A-1[N],#A-1[N],#A-1[N],#A-1[N],#A-1[N],#A-1[N],#A-1[N],#A-1[N],#A-1[N],#A-1[N],#A-1[N],#A-1[N],#A-1[N],#A-1[N],#A-1[N],#A-1[N],#A-1[N],#A-1[N],#A-1[N],#A-1[N],#A-1[N],#A-1[N],#A-1[N],#A-1[N],#A-1[N],#A-1[N],#A-1[N],#A-1[N],#A-1[N],#A-1[N],#A-1[N],#A-1[N],#A-1[N],#A-1[N],#A-1[N],#A-1[N],#A-1[N],#A-1[N],#A-1[N],#A-1[N],#A-1[N],#A-1[N],#A-1[N],#A-1[N],#A-1[N],#A-1[N],#A-1[N],#A-1[N],#A-1[N],#A-1[N],#A-1[N],#A-1[N],#A-1[N],#A-1[N],#A-1[N],#A-1[N],#A-1[N],#A-1[N],#A-1[N],#A-1[N],#A-1[N],#A-1[N],#A-1[N],#A-1[N],#A-1[N],#A-1[N],#A-1[N],#A-1[N],#A-1[N],#A-1[N],#A-1[N],#A-1[N],#A-1[N],#A-1[N],#A-1[N],#A-1[N],#A-1[N],#A-1[N],#A-1[N],#A-1[N],#A-1[N],#A-1[N],#A-1[N],#A-1[N],#A-1[N],#A-1[N],#A-1[N],#A-1[N],#A-1[N],#A-1[N],#A-1[N],#A-1[N],#A-1[N],#A-1[N],#A-1[N],#A-1[N],#A-1[N],#A-1[N],#A-1[N],#A-1[N],#A-1[N],#A-1[N],#A-1[N],#A-1[N],#A-1[N],#A-1[N],#A-1[N],#A-1[N],#A-1[N],#A-1[N],#A-1[N],#A-1[N],#A-1[N],#A-1[N],#A-1[N],#A-1[N],#A-1[N],#A-1[N],#A-1[N],#A-1[N],#A-1[N],#A-1[N],#A-1[N],#A-1[N],#A-1[N],#A-1[N],#A-1[N],#A-1[N],#A-1[N],#A-1[N],#A-1[N],#A-1[N],#A-1[N],#A-1[N],#A-1[N],#A-1[N],#A-1[N],#A-1[N],#A-1[N],#A-1[N],#A-1[N],#A-1[N],#A-1[N],#A-1[N],#A-1[N],#A-1[N],#A-1[N],#A-1[N],#A-1[N],#A-1[N],#A-1[N],#A-1[N],#A-1[N],#A-1[N],#A-1[N],#A-1[N],#A-1[N],#A-1[N],#A-1[N],#A-1[N],#A-1[N],#A-1[N],#A-1[N],#A-1[N],#A-1[N],#A-1[N],#A-1[N],#A-1[N],#A-1[N],#A-1[N],#A-1[N],#A-1[N],#A-1[N],#A-1[N],#A-1[N],#A-1[N],#A-1[N],#A-1[N],#A-1[N],#A-1[N],#A-1[N],#A-1[N],#A-1[N],#A-1[N],#A-1[N],#A-1[N],#A-1[N],#A-1[N],#A-1[N],#A-1[N],#A-1[N],#A-1[N],#A-1[N],#A-1[N],#A-1[N],c[N],c[N],c[N],c[N],c[N],c[N],c[N],c[N],c[N],c[N],c[N],c[N],c[N],c[N],c[N],c[N],c[N],c[N],c[N],c[N],c[N],c[N],c[N],c[N],c[N],c[N],c[N],c[N],c[N],c[N],c[N],c[N],c[N],c[N],c[N],c[N],c[N],c[N],c[N],c[N],c[N],c[N],c[N],c[N],c[N],c[N],c[N],c[N],c[N],c[N],c[N],c[N],c[N],c[N],c[N],c[N],c[N],c[N],c[N],c[N],c[N],c[N],c[N],c[N],c[N],c[N],c[N],c[N],c[N],c[N],c[N],c[N],c[N],c[N],c[N],c[N],c[N],c[N],c[N],c[N],c[N],c[N],c[N],c[N],c[N],c[N],c[N],c[N],c[N],c[N],c[N],c[N],c[N],c[N],c[N],c[N],c[N],c[N],c[N],c[N],c[N],c[N],c[N],c[N],c[N],c[N],c[N],c[N],c[N],c[N],c[N],c[N],c[N],c[N],c[N],c[N],c[N],c[N],c[N],c[N],c[N],c[N],c[N],c[N],c[N],c[N],c[N],c[N],c[N],c[N],c[N],c[N],c[N],c[N],c[N],c[N],c[N],c[N],c[N],c[N],c[N],c[N],c[N],c[N],c[N],c[N],c[N],c[N],c[N],c[N],c[N],c[N],c[N],c[N],c[N],c[N],c[N],c[N],c[N],c[N],c[N],c[N],c[N],c[N],c[N],c[N],c[N],c[N],c[N],c[N],c[N],c[N],c[N],c[N],c[N],c[N],c[N],c[N],c[N],c[N],c[N],c[N],c[N],c[N],c[N],c[N],c[N],c[N],c[N],c[N],c[N],c[N],c[N],c[N],c[N],c[N],c[N],c[N],c[N],c[N],c[N],c[N],c[N],c[N],c[N],c[N],c[N],c[N],c[N],c[N],c[N],c[N],c[N],c[N],c[N],c[N],c[N],c[N],c[N],c[N],c[N],c[N],c[N],c[N],c[N],c[N],c[N],c[N],c[N],c[N],c[N],c[N],c[N],c[N],c[N],c[N],c[N],c[N],c[N],c[N],c[N],c[N],c[N],c[N],c[N],c[N],c[N],c[N],c[N],c[N],c[N],c[N],c[N],c[N],c[N],c[N],#A-1[N],#A-1[N],#A-1[N],#A-1[N],#A-1[N],#A-1[N],#A-1[N],#A-1[N],#A-1[N],#A-1[N],#A-1[N],#A-1[N],#A-1[N],#A-1[N],#A-1[N],#A-1[N],#A-1[N],#A-1[N],#A-1[N],#A-1[N],#A-1[N],#A-1[N],#A-1[N],#A-1[N],#A-1[N],#A-1[N],#A-1[N],#A-1[N],#A-1[N],#A-1[N],#A-1[N],#A-1[N],#A-1[N],#A-1[N],#A-1[N],#A-1[N],#A-1[N],#A-1[N],#A-1[N],#A-1[N],#A-1[N],#A-1[N],#A-1[N],#A-1[N],#A-1[N],#A-1[N],#A-1[N],#A-1[N],#A-1[N],#A-1[N],#A-1[N],#A-1[N],#A-1[N],#A-1[N],#A-1[N],#A-1[N],#A-1[N],#A-1[N],#A-1[N],#A-1[N],#A-1[N],#A-1[N],#A-1[N],#A-1[N],#A-1[N],#A-1[N],#A-1[N],#A-1[N],#A-1[N],#A-1[N],#A-1[N],#A-1[N],#A-1[N],#A-1[N],#A-1[N],#A-1[N],#A-1[N],#A-1[N],#A-1[N],#A-1[N],#A-1[N],#A-1[N],#A-1[N],#A-1[N],#A-1[N],#A-1[N],#A-1[N],#A-1[N],#A-1[N],#A-1[N],#A-1[N],#A-1[N],#A-1[N],#A-1[N],#A-1[N],#A-1[N],#A-1[N],#A-1[N],#A-1[N],#A-1[N],#A-1[N],#A-1[N],#A-1[N],#A-1[N],#A-1[N],#A-1[N],#A-1[N],#A-1[N],#A-1[N],#A-1[N],#A-1[N],#A-1[N],#A-1[N],#A-1[N],#A-1[N],#A-1[N],#A-1[N],#A-1[N],#A-1[N],#A-1[N],#A-1[N],#A-1[N],#A-1[N],#A-1[N],#A-1[N],#A-1[N],#A-1[N],#A-1[N],#A-1[N],#A-1[N],#A-1[N],#A-1[N],#A-1[N],#A-1[N],#A-1[N],#A-1[N],#A-1[N],#A-1[N],#A-1[N],#A-1[N],#A-1[N],#A-1[N],#A-1[N],#A-1[N],#A-1[N],#A-1[N],#A-1[N],#A-1[N],#A-1[N],#A-1[N],#A-1[N],#A-1[N],#A-1[N],#A-1[N],#A-1[N],#A-1[N],#A-1[N],#A-1[N],#A-1[N],#A-1[N],#A-1[N],#A-1[N],#A-1[N],#A-1[N],#A-1[N],#A-1[N],#A-1[N],#A-1[N],#A-1[N],#A-1[N],#A-1[N],#A-1[N],#A-1[N],#A-1[N],#A-1[N],#A-1[N],#A-1[N],#A-1[N],#A-1[N],#A-1[N],#A-1[N],#A-1[N],#A-1[N],#A-1[N],#A-1[N],#A-1[N],#A-1[N],#A-1[N],#A-1[N],#A-1[N],#A-1[N],#A-1[N],#A-1[N],#A-1[N],#A-1[N],#A-1[N],#A-1[N],#A-1[N],#A-1[N],#A-1[N],#A-1[N],#A-1[N],#A-1[N],#A-1[N],#A-1[N],#A-1[N],#A-1[N],#A-1[N],#A-1[N],#A-1[N],#A-1[N],#A-1[N],#A-1[N],#A-1[N],#A-1[N],#A-1[N],#A-1[N],#A-1[N],#A-1[N],#A-1[N],#A-1[N],#A-1[N],#A-1[N],#A-1[N],#A-1[N],#A-1[N],#A-1[N],#A-1[N],#A-1[N],#A-1[N],#A-1[N],#A-1[N],#A-1[N],#A-1[N],#A-1[N],#A-1[N],#A-1[N],#A-1[N],#A-1[N],#A-1[N],#A-1[N],#A-1[N],#A-1[N],#A-1[N],#A-1[N],#A-1[N],#A-1[N],#A-1[N],#A-1[N],#A-1[N],#A-1[N],#A-1[N],#A-1[N],#A-1[N],#A-1[N],#A-1[N],c[N],c[N],c[N],c[N],c[N],c[N],c[N],c[N],c[N],c[N],c[N],c[N],c[N],c[N],c[N],c[N],c[N],c[N],c[N],c[N],c[N],c[N],c[N],c[N],c[N],c[N],c[N],c[N],c[N],c[N],c[N],c[N],c[N],c[N],c[N],c[N],c[N],c[N],c[N],c[N],c[N],c[N],c[N],c[N],c[N],c[N],c[N],c[N],c[N],c[N],c[N],c[N],c[N],c[N],c[N],c[N],c[N],c[N],c[N],c[N],c[N],c[N],c[N],c[N],c[N],c[N],c[N],c[N],c[N],c[N],c[N],c[N],c[N],c[N],c[N],c[N],c[N],c[N],c[N],c[N],c[N],c[N],c[N],c[N],c[N],c[N],c[N],c[N],c[N],c[N],c[N],c[N],c[N],c[N],c[N],c[N],c[N],c[N],c[N],c[N],c[N],c[N],c[N],c[N],c[N],c[N],c[N],c[N],c[N],c[N],c[N],c[N],c[N],c[N],c[N],c[N],c[N],c[N],c[N],c[N],c[N],c[N],c[N],c[N],c[N],c[N],c[N],c[N],c[N],c[N],c[N],c[N],c[N],c[N],c[N],c[N],c[N],c[N],c[N],c[N],c[N],c[N],c[N],c[N],c[N],c[N],c[N],c[N],c[N],c[N],c[N],c[N],c[N],c[N],c[N],c[N],c[N],c[N],c[N],c[N],c[N],c[N],c[N],c[N],c[N],c[N],c[N],c[N],c[N],c[N],c[N],c[N],c[N],c[N],c[N],c[N],c[N],c[N],c[N],c[N],c[N],c[N],c[N],c[N],c[N],c[N],c[N],c[N],c[N],c[N],c[N],c[N],c[N],c[N],c[N],c[N],c[N],c[N],c[N],c[N],c[N],c[N],c[N],c[N],c[N],c[N],c[N],c[N],c[N],c[N],c[N],c[N],c[N],c[N],c[N],c[N],c[N],c[N],c[N],c[N],c[N],c[N],c[N],c[N],c[N],c[N],c[N],c[N],c[N],c[N],c[N],c[N],c[N],c[N],c[N],c[N],c[N],c[N],c[N],c[N],c[N],c[N],c[N],c[N],c[N],c[N],c[N],c[N],c[N],c[N],c[N],c[N],c[N],c[N],c[N],c[N],#A-1[N],#A-1[N],#A-1[N],#A-1[N],#A-1[N],#A-1[N],#A-1[N],#A-1[N],#A-1[N],#A-1[N],#A-1[N],#A-1[N],#A-1[N],#A-1[N],#A-1[N],#A-1[N],#A-1[N],#A-1[N],#A-1[N],#A-1[N],#A-1[N],#A-1[N],#A-1[N],#A-1[N],#A-1[N],#A-1[N],#A-1[N],#A-1[N],#A-1[N],#A-1[N],#A-1[N],#A-1[N],#A-1[N],#A-1[N],#A-1[N],#A-1[N],#A-1[N],#A-1[N],#A-1[N],#A-1[N],#A-1[N],#A-1[N],#A-1[N],#A-1[N],#A-1[N],#A-1[N],#A-1[N],#A-1[N],#A-1[N],#A-1[N],#A-1[N],#A-1[N],#A-1[N],#A-1[N],#A-1[N],#A-1[N],#A-1[N],#A-1[N],#A-1[N],#A-1[N],#A-1[N],#A-1[N],#A-1[N],#A-1[N],#A-1[N],#A-1[N],#A-1[N],#A-1[N],#A-1[N],#A-1[N],#A-1[N],#A-1[N],#A-1[N],#A-1[N],#A-1[N],#A-1[N],#A-1[N],#A-1[N],#A-1[N],#A-1[N],#A-1[N],#A-1[N],#A-1[N],#A-1[N],#A-1[N],#A-1[N],#A-1[N],#A-1[N],#A-1[N],#A-1[N],#A-1[N],#A-1[N],#A-1[N],#A-1[N],#A-1[N],#A-1[N],#A-1[N],#A-1[N],#A-1[N],#A-1[N],#A-1[N],#A-1[N],#A-1[N],#A-1[N],#A-1[N],#A-1[N],#A-1[N],#A-1[N],#A-1[N],#A-1[N],#A-1[N],#A-1[N],#A-1[N],#A-1[N],#A-1[N],#A-1[N],#A-1[N],#A-1[N],#A-1[N],#A-1[N],#A-1[N],#A-1[N],#A-1[N],#A-1[N],#A-1[N],#A-1[N],#A-1[N],#A-1[N],#A-1[N],#A-1[N],#A-1[N],#A-1[N],#A-1[N],#A-1[N],#A-1[N],#A-1[N],#A-1[N],#A-1[N],#A-1[N],#A-1[N],#A-1[N],#A-1[N],#A-1[N],#A-1[N],#A-1[N],#A-1[N],#A-1[N],#A-1[N],#A-1[N],#A-1[N],#A-1[N],#A-1[N],#A-1[N],#A-1[N],#A-1[N],#A-1[N],#A-1[N],#A-1[N],#A-1[N],#A-1[N],#A-1[N],#A-1[N],#A-1[N],#A-1[N],#A-1[N],#A-1[N],#A-1[N],#A-1[N],#A-1[N],#A-1[N],#A-1[N],#A-1[N],#A-1[N],#A-1[N],#A-1[N],#A-1[N],#A-1[N],#A-1[N],#A-1[N],#A-1[N],#A-1[N],#A-1[N],#A-1[N],#A-1[N],#A-1[N],#A-1[N],#A-1[N],#A-1[N],#A-1[N],#A-1[N],#A-1[N],#A-1[N],#A-1[N],#A-1[N],#A-1[N],#A-1[N],#A-1[N],#A-1[N],#A-1[N],#A-1[N],#A-1[N],#A-1[N],#A-1[N],#A-1[N],#A-1[N],#A-1[N],#A-1[N],#A-1[N],#A-1[N],#A-1[N],#A-1[N],#A-1[N],#A-1[N],#A-1[N],#A-1[N],#A-1[N],#A-1[N],#A-1[N],#A-1[N],#A-1[N],#A-1[N],#A-1[N],#A-1[N],#A-1[N],#A-1[N],#A-1[N],#A-1[N],#A-1[N],#A-1[N],#A-1[N],#A-1[N],#A-1[N],#A-1[N],#A-1[N],#A-1[N],#A-1[N],#A-1[N],#A-1[N],#A-1[N],#A-1[N],#A-1[N],#A-1[N],#A-1[N],#A-1[N],#A-1[N],#A-1[N],#A-1[N],#A-1[N],#A-1[N],#A-1[N],#A-1[N],#A-1[N],#A-1[N],#A-1[N],#A-1[N],#A-1[N],c[N],c[N],c[N],c[N],c[N],c[N],c[N],c[N],c[N],c[N],c[N],c[N],c[N],c[N],c[N],c[N],c[N],c[N],c[N],c[N],c[N],c[N],c[N],c[N],c[N],c[N],c[N],c[N],c[N],c[N],c[N],c[N],c[N],c[N],c[N],c[N],c[N],c[N],c[N],c[N],c[N],c[N],c[N],c[N],c[N],c[N],c[N],c[N],c[N],c[N],c[N],c[N],c[N],c[N],c[N],c[N],c[N],c[N],c[N],c[N],c[N],c[N],c[N],c[N],c[N],c[N],c[N],c[N],c[N],c[N],c[N],c[N],c[N],c[N],c[N],c[N],c[N],c[N],c[N],c[N],c[N],c[N],c[N],c[N],c[N],c[N],c[N],c[N],c[N],c[N],c[N],c[N],c[N],c[N],c[N],c[N],c[N],c[N],c[N],c[N],c[N],c[N],c[N],c[N],c[N],c[N],c[N],c[N],c[N],c[N],c[N],c[N],c[N],c[N],c[N],c[N],c[N],c[N],c[N],c[N],c[N],c[N],c[N],c[N],c[N],c[N],c[N],c[N],c[N],c[N],c[N],c[N],c[N],c[N],c[N],c[N],c[N],c[N],c[N],c[N],c[N],c[N],c[N],c[N],c[N],c[N],c[N],c[N],c[N],c[N],c[N],c[N],c[N],c[N],c[N],c[N],c[N],c[N],c[N],c[N],c[N],c[N],c[N],c[N],c[N],c[N],c[N],c[N],c[N],c[N],c[N],c[N],c[N],c[N],c[N],c[N],c[N],c[N],c[N],c[N],c[N],c[N],c[N],c[N],c[N],c[N],c[N],c[N],c[N],c[N],c[N],c[N],c[N],c[N],c[N],c[N],c[N],c[N],c[N],c[N],c[N],c[N],c[N],c[N],c[N],c[N],c[N],c[N],c[N],c[N],c[N],c[N],c[N],c[N],c[N],c[N],c[N],c[N],c[N],c[N],c[N],c[N],c[N],c[N],c[N],c[N],c[N],c[N],c[N],c[N],c[N],c[N],c[N],c[N],c[N],c[N],c[N],c[N],c[N],c[N],c[N],c[N],c[N],c[N],c[N],c[N],c[N],c[N],c[N],c[N],c[N],c[N],c[N],c[N],c[N],c[N],#A-1[N],#A-1[N],#A-1[N],#A-1[N],#A-1[N],#A-1[N],#A-1[N],#A-1[N],#A-1[N],#A-1[N],#A-1[N],#A-1[N],#A-1[N],#A-1[N],#A-1[N],#A-1[N],#A-1[N],#A-1[N],#A-1[N],#A-1[N],#A-1[N],#A-1[N],#A-1[N],#A-1[N],#A-1[N],#A-1[N],#A-1[N],#A-1[N],#A-1[N],#A-1[N],#A-1[N],#A-1[N],#A-1[N],#A-1[N],#A-1[N],#A-1[N],#A-1[N],#A-1[N],#A-1[N],#A-1[N],#A-1[N],#A-1[N],#A-1[N],#A-1[N],#A-1[N],#A-1[N],#A-1[N],#A-1[N],#A-1[N],#A-1[N],#A-1[N],#A-1[N],#A-1[N],#A-1[N],#A-1[N],#A-1[N],#A-1[N],#A-1[N],#A-1[N],#A-1[N],#A-1[N],#A-1[N],#A-1[N],#A-1[N],#A-1[N],#A-1[N],#A-1[N],#A-1[N],#A-1[N],#A-1[N],#A-1[N],#A-1[N],#A-1[N],#A-1[N],#A-1[N],#A-1[N],#A-1[N],#A-1[N],#A-1[N],#A-1[N],#A-1[N],#A-1[N],#A-1[N],#A-1[N],#A-1[N],#A-1[N],#A-1[N],#A-1[N],#A-1[N],#A-1[N],#A-1[N],#A-1[N],#A-1[N],#A-1[N],#A-1[N],#A-1[N],#A-1[N],#A-1[N],#A-1[N],#A-1[N],#A-1[N],#A-1[N],#A-1[N],#A-1[N],#A-1[N],#A-1[N],#A-1[N],#A-1[N],#A-1[N],#A-1[N],#A-1[N],#A-1[N],#A-1[N],#A-1[N],#A-1[N],#A-1[N],#A-1[N],#A-1[N],#A-1[N],#A-1[N],#A-1[N],#A-1[N],#A-1[N],#A-1[N],#A-1[N],#A-1[N],#A-1[N],#A-1[N],#A-1[N],#A-1[N],#A-1[N],#A-1[N],#A-1[N],#A-1[N],#A-1[N],#A-1[N],#A-1[N],#A-1[N],#A-1[N],#A-1[N],#A-1[N],#A-1[N],#A-1[N],#A-1[N],#A-1[N],#A-1[N],#A-1[N],#A-1[N],#A-1[N],#A-1[N],#A-1[N],#A-1[N],#A-1[N],#A-1[N],#A-1[N],#A-1[N],#A-1[N],#A-1[N],#A-1[N],#A-1[N],#A-1[N],#A-1[N],#A-1[N],#A-1[N],#A-1[N],#A-1[N],#A-1[N],#A-1[N],#A-1[N],#A-1[N],#A-1[N],#A-1[N],#A-1[N],#A-1[N],#A-1[N],#A-1[N],#A-1[N],#A-1[N],#A-1[N],#A-1[N],#A-1[N],#A-1[N],#A-1[N],#A-1[N],#A-1[N],#A-1[N],#A-1[N],#A-1[N],#A-1[N],#A-1[N],#A-1[N],#A-1[N],#A-1[N],#A-1[N],#A-1[N],#A-1[N],#A-1[N],#A-1[N],#A-1[N],#A-1[N],#A-1[N],#A-1[N],#A-1[N],#A-1[N],#A-1[N],#A-1[N],#A-1[N],#A-1[N],#A-1[N],#A-1[N],#A-1[N],#A-1[N],#A-1[N],#A-1[N],#A-1[N],#A-1[N],#A-1[N],#A-1[N],#A-1[N],#A-1[N],#A-1[N],#A-1[N],#A-1[N],#A-1[N],#A-1[N],#A-1[N],#A-1[N],#A-1[N],#A-1[N],#A-1[N],#A-1[N],#A-1[N],#A-1[N],#A-1[N],#A-1[N],#A-1[N],#A-1[N],#A-1[N],#A-1[N],#A-1[N],#A-1[N],#A-1[N],#A-1[N],#A-1[N],#A-1[N],#A-1[N],#A-1[N],#A-1[N],#A-1[N],#A-1[N],#A-1[N],#A-1[N],#A-1[N],#A-1[N],#A-1[N],#A-1[N],c[N],c[N],c[N],c[N],c[N],c[N],c[N],c[N],c[N],c[N],c[N],c[N],c[N],c[N],c[N],c[N],c[N],c[N],c[N],c[N],c[N],c[N],c[N],c[N],c[N],c[N],c[N],c[N],c[N],c[N],c[N],c[N],c[N],c[N],c[N],c[N],c[N],c[N],c[N],c[N],c[N],c[N],c[N],c[N],c[N],c[N],c[N],c[N],c[N],c[N],c[N],c[N],c[N],c[N],c[N],c[N],c[N],c[N],c[N],c[N],c[N],c[N],c[N],c[N],c[N],c[N],c[N],c[N],c[N],c[N],c[N],c[N],c[N],c[N],c[N],c[N],c[N],c[N],c[N],c[N],c[N],c[N],c[N],c[N],c[N],c[N],c[N],c[N],c[N],c[N],c[N],c[N],c[N],c[N],c[N],c[N],c[N],c[N],c[N],c[N],c[N],c[N],c[N],c[N],c[N],c[N],c[N],c[N],c[N],c[N],c[N],c[N],c[N],c[N],c[N],c[N],c[N],c[N],c[N],c[N],c[N],c[N],c[N],c[N],c[N],c[N],c[N],c[N],c[N],c[N],c[N],c[N],c[N],c[N],c[N],c[N],c[N],c[N],c[N],c[N],c[N],c[N],c[N],c[N],c[N],c[N],c[N],c[N],c[N],c[N],c[N],c[N],c[N],c[N],c[N],c[N],c[N],c[N],c[N],c[N],c[N],c[N],c[N],c[N],c[N],c[N],c[N],c[N],c[N],c[N],c[N],c[N],c[N],c[N],c[N],c[N],c[N],c[N],c[N],c[N],c[N],c[N],c[N],c[N],c[N],c[N],c[N],c[N],c[N],c[N],c[N],c[N],c[N],c[N],c[N],c[N],c[N],c[N],c[N],c[N],c[N],c[N],c[N],c[N],c[N],c[N],c[N],c[N],c[N],c[N],c[N],c[N],c[N],c[N],c[N],c[N],c[N],c[N],c[N],c[N],c[N],c[N],c[N],c[N],c[N],c[N],c[N],c[N],c[N],c[N],c[N],c[N],c[N],c[N],c[N],c[N],c[N],c[N],c[N],c[N],c[N],c[N],c[N],c[N],c[N],c[N],c[N],c[N],c[N],c[N],c[N],c[N],c[N],c[N],c[N],c[N]>,7<(a~#a~b~c1~#c1~d1~#d1~e1)[K]>;"]},{"id":3,"bpm":300,"baseBeats":0.5,"scores":["f[L],a[L],d[L],d[L],3<(A-2.A-1.#c.e.a.#c1.e1.a1)[M],(A-2.A-1.#c.e.a.#c1.e1.a1)[M],(A-2.A-1.#c.e.a.#c1.e1.a1)[M],(A-2.A-1.#c.e.a.#c1.e1.a1)[M],(A-2.A-1.#c.e.a.#c1.e1.a1)[M],(A-2.A-1.#c.e.a.#c1.e1.a1)[M],(A-2.A-1.#c.e.a.#c1.e1.a1)[M],(A-2.A-1.#c.e.a.#c1.e1.a1)[M],(A-2.A-1.#c.e.a.#c1.e1.a1)[M],(A-2.A-1.#c.e.a.#c1.e1.a1)[M],(A-2.A-1.#c.e.a.#c1.e1.a1)[M],(A-2.A-1.#c.e.a.#c1.e1.a1)[M],(A-2.A-1.#c.e.a.#c1.e1.a1)[M],(A-2.A-1.#c.e.a.#c1.e1.a1)[M],(A-2.A-1.#c.e.a.#c1.e1.a1)[M],(A-2.A-1.#c.e.a.#c1.e1.a1)[M],(A-2.A-1.#c.e.a.#c1.e1.a1)[M],(A-2.A-1.#c.e.a.#c1.e1.a1)[M],(A-2.A-1.#c.e.a.#c1.e1.a1)[M],(A-2.A-1.#c.e.a.#c1.e1.a1)[M],(A-2.A-1.#c.e.a.#c1.e1.a1)[M],(A-2.A-1.#c.e.a.#c1.e1.a1)[M],(A-2.A-1.#c.e.a.#c1.e1.a1)[M],(A-2.A-1.#c.e.a.#c1.e1.a1)[M],(A-2.A-1.#c.e.a.#c1.e1.a1)[M],(A-2.A-1.#c.e.a.#c1.e1.a1)[M],(A-2.A-1.#c.e.a.#c1.e1.a1)[M],(A-2.A-1.#c.e.a.#c1.e1.a1)[M],(A-2.A-1.#c.e.a.#c1.e1.a1)[M],(A-2.A-1.#c.e.a.#c1.e1.a1)[M],(A-2.A-1.#c.e.a.#c1.e1.a1)[M],(A-2.A-1.#c.e.a.#c1.e1.a1)[M],(A-2.A-1.#c.e.a.#c1.e1.a1)[M],(A-2.A-1.#c.e.a.#c1.e1.a1)[M],(A-2.A-1.#c.e.a.#c1.e1.a1)[M],(A-2.A-1.#c.e.a.#c1.e1.a1)[M],(A-2.A-1.#c.e.a.#c1.e1.a1)[M],(A-2.A-1.#c.e.a.#c1.e1.a1)[M],(A-2.A-1.#c.e.a.#c1.e1.a1)[M],(A-2.A-1.#c.e.a.#c1.e1.a1)[M],(A-2.A-1.#c.e.a.#c1.e1.a1)[M],(A-2.A-1.#c.e.a.#c1.e1.a1)[M],(A-2.A-1.#c.e.a.#c1.e1.a1)[M],(A-2.A-1.#c.e.a.#c1.e1.a1)[M],(A-2.A-1.#c.e.a.#c1.e1.a1)[M],(A-2.A-1.#c.e.a.#c1.e1.a1)[M],(A-2.A-1.#c.e.a.#c1.e1.a1)[M],(A-2.A-1.#c.e.a.#c1.e1.a1)[M],(A-2.A-1.#c.e.a.#c1.e1.a1)[M],(A-2.A-1.#c.e.a.#c1.e1.a1)[M],(A-2.A-1.#c.e.a.#c1.e1.a1)[M],(A-2.A-1.#c.e.a.#c1.e1.a1)[M],(A-2.A-1.#c.e.a.#c1.e1.a1)[M],(A-2.A-1.#c.e.a.#c1.e1.a1)[M],(A-2.A-1.#c.e.a.#c1.e1.a1)[M],(A-2.A-1.#c.e.a.#c1.e1.a1)[M],(A-2.A-1.#c.e.a.#c1.e1.a1)[M],(A-2.A-1.#c.e.a.#c1.e1.a1)[M],(A-2.A-1.#c.e.a.#c1.e1.a1)[M],(A-2.A-1.#c.e.a.#c1.e1.a1)[M],(A-2.A-1.#c.e.a.#c1.e1.a1)[M],(A-2.A-1.#c.e.a.#c1.e1.a1)[M],(A-2.A-1.#c.e.a.#c1.e1.a1)[M],(A-2.A-1.#c.e.a.#c1.e1.a1)[M],(A-2.A-1.#c.e.a.#c1.e1.a1)[M],(A-2.A-1.#c.e.a.#c1.e1.a1)[M],(A-2.A-1.#c.e.a.#c1.e1.a1)[M],(A-2.A-1.#c.e.a.#c1.e1.a1)[M],(A-2.A-1.#c.e.a.#c1.e1.a1)[M],(A-2.A-1.#c.e.a.#c1.e1.a1)[M],(A-2.A-1.#c.e.a.#c1.e1.a1)[M],(A-2.A-1.#c.e.a.#c1.e1.a1)[M],(A-2.A-1.#c.e.a.#c1.e1.a1)[M],(A-2.A-1.#c.e.a.#c1.e1.a1)[M],(A-2.A-1.#c.e.a.#c1.e1.a1)[M],(A-2.A-1.#c.e.a.#c1.e1.a1)[M],(A-2.A-1.#c.e.a.#c1.e1.a1)[M],(A-2.A-1.#c.e.a.#c1.e1.a1)[M],(A-2.A-1.#c.e.a.#c1.e1.a1)[M],(A-2.A-1.#c.e.a.#c1.e1.a1)[M],(A-2.A-1.#c.e.a.#c1.e1.a1)[M],(A-2.A-1.#c.e.a.#c1.e1.a1)[M],(A-2.A-1.#c.e.a.#c1.e1.a1)[M],(A-2.A-1.#c.e.a.#c1.e1.a1)[M],(A-2.A-1.#c.e.a.#c1.e1.a1)[M],(A-2.A-1.#c.e.a.#c1.e1.a1)[M],(A-2.A-1.#c.e.a.#c1.e1.a1)[M],(A-2.A-1.#c.e.a.#c1.e1.a1)[M],(A-2.A-1.#c.e.a.#c1.e1.a1)[M],(A-2.A-1.#c.e.a.#c1.e1.a1)[M],(A-2.A-1.#c.e.a.#c1.e1.a1)[M],(A-2.A-1.#c.e.a.#c1.e1.a1)[M],(A-2.A-1.#c.e.a.#c1.e1.a1)[M],(A-2.A-1.#c.e.a.#c1.e1.a1)[M],(A-2.A-1.#c.e.a.#c1.e1.a1)[M],(A-2.A-1.#c.e.a.#c1.e1.a1)[M],(A-2.A-1.#c.e.a.#c1.e1.a1)[M],(A-2.A-1.#c.e.a.#c1.e1.a1)[M],(A-2.A-1.#c.e.a.#c1.e1.a1)[M],(A-2.A-1.#c.e.a.#c1.e1.a1)[M],(A-2.A-1.#c.e.a.#c1.e1.a1)[M],(A-2.A-1.#c.e.a.#c1.e1.a1)[M],(A-2.A-1.#c.e.a.#c1.e1.a1)[M],(A-2.A-1.#c.e.a.#c1.e1.a1)[M],(A-2.A-1.#c.e.a.#c1.e1.a1)[M],(A-2.A-1.#c.e.a.#c1.e1.a1)[M],(A-2.A-1.#c.e.a.#c1.e1.a1)[M],(A-2.A-1.#c.e.a.#c1.e1.a1)[M],(A-2.A-1.#c.e.a.#c1.e1.a1)[M],(A-2.A-1.#c.e.a.#c1.e1.a1)[M],(A-2.A-1.#c.e.a.#c1.e1.a1)[M],(A-2.A-1.#c.e.a.#c1.e1.a1)[M],(A-2.A-1.#c.e.a.#c1.e1.a1)[M],(A-2.A-1.#c.e.a.#c1.e1.a1)[M],(A-2.A-1.#c.e.a.#c1.e1.a1)[M],(A-2.A-1.#c.e.a.#c1.e1.a1)[M],(A-2.A-1.#c.e.a.#c1.e1.a1)[M],(A-2.A-1.#c.e.a.#c1.e1.a1)[M],(A-2.A-1.#c.e.a.#c1.e1.a1)[M],(A-2.A-1.#c.e.a.#c1.e1.a1)[M],(A-2.A-1.#c.e.a.#c1.e1.a1)[M],(A-2.A-1.#c.e.a.#c1.e1.a1)[M],(A-2.A-1.#c.e.a.#c1.e1.a1)[M],(A-2.A-1.#c.e.a.#c1.e1.a1)[M],(A-2.A-1.#c.e.a.#c1.e1.a1)[M],(A-2.A-1.#c.e.a.#c1.e1.a1)[M],(A-2.A-1.#c.e.a.#c1.e1.a1)[M],(A-2.A-1.#c.e.a.#c1.e1.a1)[M],(A-2.A-1.#c.e.a.#c1.e1.a1)[M],(A-2.A-1.#c.e.a.#c1.e1.a1)[M],(A-2.A-1.#c.e.a.#c1.e1.a1)[M],(A-2.A-1.#c.e.a.#c1.e1.a1)[M],(A-2.A-1.#c.e.a.#c1.e1.a1)[M],(A-2.A-1.#c.e.a.#c1.e1.a1)[M],(A-2.A-1.#c.e.a.#c1.e1.a1)[M],(A-2.A-1.#c.e.a.#c1.e1.a1)[M],(A-2.A-1.#c.e.a.#c1.e1.a1)[M],(A-2.A-1.#c.e.a.#c1.e1.a1)[M],(A-2.A-1.#c.e.a.#c1.e1.a1)[M],(A-2.A-1.#c.e.a.#c1.e1.a1)[M],(A-2.A-1.#c.e.a.#c1.e1.a1)[M],(A-2.A-1.#c.e.a.#c1.e1.a1)[M],(A-2.A-1.#c.e.a.#c1.e1.a1)[M],(A-2.A-1.#c.e.a.#c1.e1.a1)[M],(A-2.A-1.#c.e.a.#c1.e1.a1)[M],(A-2.A-1.#c.e.a.#c1.e1.a1)[M],(A-2.A-1.#c.e.a.#c1.e1.a1)[M],(A-2.A-1.#c.e.a.#c1.e1.a1)[M],(A-2.A-1.#c.e.a.#c1.e1.a1)[M],(A-2.A-1.#c.e.a.#c1.e1.a1)[M],(A-2.A-1.#c.e.a.#c1.e1.a1)[M],(A-2.A-1.#c.e.a.#c1.e1.a1)[M],(A-2.A-1.#c.e.a.#c1.e1.a1)[M],(A-2.A-1.#c.e.a.#c1.e1.a1)[M],(A-2.A-1.#c.e.a.#c1.e1.a1)[M],(A-2.A-1.#c.e.a.#c1.e1.a1)[M],(A-2.A-1.#c.e.a.#c1.e1.a1)[M],(A-2.A-1.#c.e.a.#c1.e1.a1)[M],(A-2.A-1.#c.e.a.#c1.e1.a1)[M],(A-2.A-1.#c.e.a.#c1.e1.a1)[M],(A-2.A-1.#c.e.a.#c1.e1.a1)[M],(A-2.A-1.#c.e.a.#c1.e1.a1)[M],(A-2.A-1.#c.e.a.#c1.e1.a1)[M],(A-2.A-1.#c.e.a.#c1.e1.a1)[M],(A-2.A-1.#c.e.a.#c1.e1.a1)[M],(A-2.A-1.#c.e.a.#c1.e1.a1)[M],(A-2.A-1.#c.e.a.#c1.e1.a1)[M],(A-2.A-1.#c.e.a.#c1.e1.a1)[M],(A-2.A-1.#c.e.a.#c1.e1.a1)[M],(A-2.A-1.#c.e.a.#c1.e1.a1)[M],(A-2.A-1.#c.e.a.#c1.e1.a1)[M],(A-2.A-1.#c.e.a.#c1.e1.a1)[M],(A-2.A-1.#c.e.a.#c1.e1.a1)[M],(A-2.A-1.#c.e.a.#c1.e1.a1)[M],(A-2.A-1.#c.e.a.#c1.e1.a1)[M],(A-2.A-1.#c.e.a.#c1.e1.a1)[M],(A-2.A-1.#c.e.a.#c1.e1.a1)[M],(A-2.A-1.#c.e.a.#c1.e1.a1)[M],(A-2.A-1.#c.e.a.#c1.e1.a1)[M],(A-2.A-1.#c.e.a.#c1.e1.a1)[M],(A-2.A-1.#c.e.a.#c1.e1.a1)[M],(A-2.A-1.#c.e.a.#c1.e1.a1)[M],(A-2.A-1.#c.e.a.#c1.e1.a1)[M],(A-2.A-1.#c.e.a.#c1.e1.a1)[M],(A-2.A-1.#c.e.a.#c1.e1.a1)[M],(A-2.A-1.#c.e.a.#c1.e1.a1)[M],(A-2.A-1.#c.e.a.#c1.e1.a1)[M],(A-2.A-1.#c.e.a.#c1.e1.a1)[M],(A-2.A-1.#c.e.a.#c1.e1.a1)[M],(A-2.A-1.#c.e.a.#c1.e1.a1)[M],(A-2.A-1.#c.e.a.#c1.e1.a1)[M],(A-2.A-1.#c.e.a.#c1.e1.a1)[M],(A-2.A-1.#c.e.a.#c1.e1.a1)[M],(A-2.A-1.#c.e.a.#c1.e1.a1)[M],(A-2.A-1.#c.e.a.#c1.e1.a1)[M],(A-2.A-1.#c.e.a.#c1.e1.a1)[M],(A-2.A-1.#c.e.a.#c1.e1.a1)[M],(A-2.A-1.#c.e.a.#c1.e1.a1)[M],(A-2.A-1.#c.e.a.#c1.e1.a1)[M],(A-2.A-1.#c.e.a.#c1.e1.a1)[M],(A-2.A-1.#c.e.a.#c1.e1.a1)[M],(A-2.A-1.#c.e.a.#c1.e1.a1)[M],(A-2.A-1.#c.e.a.#c1.e1.a1)[M],(A-2.A-1.#c.e.a.#c1.e1.a1)[M],(A-2.A-1.#c.e.a.#c1.e1.a1)[M],(A-2.A-1.#c.e.a.#c1.e1.a1)[M],(A-2.A-1.#c.e.a.#c1.e1.a1)[M],(A-2.A-1.#c.e.a.#c1.e1.a1)[M],(A-2.A-1.#c.e.a.#c1.e1.a1)[M],(A-2.A-1.#c.e.a.#c1.e1.a1)[M],(A-2.A-1.#c.e.a.#c1.e1.a1)[M],(A-2.A-1.#c.e.a.#c1.e1.a1)[M],(A-2.A-1.#c.e.a.#c1.e1.a1)[M],(A-2.A-1.#c.e.a.#c1.e1.a1)[M],(A-2.A-1.#c.e.a.#c1.e1.a1)[M],(A-2.A-1.#c.e.a.#c1.e1.a1)[M],(A-2.A-1.#c.e.a.#c1.e1.a1)[M],(A-2.A-1.#c.e.a.#c1.e1.a1)[M],(A-2.A-1.#c.e.a.#c1.e1.a1)[M],(A-2.A-1.#c.e.a.#c1.e1.a1)[M],(A-2.A-1.#c.e.a.#c1.e1.a1)[M],(A-2.A-1.#c.e.a.#c1.e1.a1)[M],(A-2.A-1.#c.e.a.#c1.e1.a1)[M],(A-2.A-1.#c.e.a.#c1.e1.a1)[M],(A-2.A-1.#c.e.a.#c1.e1.a1)[M],(A-2.A-1.#c.e.a.#c1.e1.a1)[M],(A-2.A-1.#c.e.a.#c1.e1.a1)[M],(A-2.A-1.#c.e.a.#c1.e1.a1)[M],(A-2.A-1.#c.e.a.#c1.e1.a1)[M],(A-2.A-1.#c.e.a.#c1.e1.a1)[M],(A-2.A-1.#c.e.a.#c1.e1.a1)[M],(A-2.A-1.#c.e.a.#c1.e1.a1)[M],(A-2.A-1.#c.e.a.#c1.e1.a1)[M],(A-2.A-1.#c.e.a.#c1.e1.a1)[M],(A-2.A-1.#c.e.a.#c1.e1.a1)[M],(A-2.A-1.#c.e.a.#c1.e1.a1)[M],(A-2.A-1.#c.e.a.#c1.e1.a1)[M],(A-2.A-1.#c.e.a.#c1.e1.a1)[M],(A-2.A-1.#c.e.a.#c1.e1.a1)[M],(A-2.A-1.#c.e.a.#c1.e1.a1)[M],(A-2.A-1.#c.e.a.#c1.e1.a1)[M],(A-2.A-1.#c.e.a.#c1.e1.a1)[M],(A-2.A-1.#c.e.a.#c1.e1.a1)[M],(A-2.A-1.#c.e.a.#c1.e1.a1)[M],(A-2.A-1.#c.e.a.#c1.e1.a1)[M],(A-2.A-1.#c.e.a.#c1.e1.a1)[M],(A-2.A-1.#c.e.a.#c1.e1.a1)[M],(A-2.A-1.#c.e.a.#c1.e1.a1)[M],(A-2.A-1.#c.e.a.#c1.e1.a1)[M],(A-2.A-1.#c.e.a.#c1.e1.a1)[M],(A-2.A-1.#c.e.a.#c1.e1.a1)[M],(A-2.A-1.#c.e.a.#c1.e1.a1)[M],(A-2.A-1.#c.e.a.#c1.e1.a1)[M],(A-2.A-1.#c.e.a.#c1.e1.a1)[M],(A-2.A-1.#c.e.a.#c1.e1.a1)[M],(A-2.A-1.#c.e.a.#c1.e1.a1)[M],(A-2.A-1.#c.e.a.#c1.e1.a1)[M],(A-2.A-1.#c.e.a.#c1.e1.a1)[M],(A-2.A-1.#c.e.a.#c1.e1.a1)[M],(A-2.A-1.#c.e.a.#c1.e1.a1)[M],(A-2.A-1.#c.e.a.#c1.e1.a1)[M],(A-2.A-1.#c.e.a.#c1.e1.a1)[M],(A-2.A-1.#c.e.a.#c1.e1.a1)[M],(A-2.A-1.#c.e.a.#c1.e1.a1)[M],(A-2.A-1.#c.e.a.#c1.e1.a1)[M],(A-2.A-1.#c.e.a.#c1.e1.a1)[M],(A-2.A-1.#c.e.a.#c1.e1.a1)[M],(A-2.A-1.#c.e.a.#c1.e1.a1)[M],(A-2.A-1.#c.e.a.#c1.e1.a1)[M],(A-2.A-1.#c.e.a.#c1.e1.a1)[M],(A-2.A-1.#c.e.a.#c1.e1.a1)[M],(A-2.A-1.#c.e.a.#c1.e1.a1)[M],(A-2.A-1.#c.e.a.#c1.e1.a1)[M],(A-2.A-1.#c.e.a.#c1.e1.a1)[M],(A-2.A-1.#c.e.a.#c1.e1.a1)[M],(A-2.A-1.#c.e.a.#c1.e1.a1)[M],(A-2.A-1.#c.e.a.#c1.e1.a1)[M],(A-2.A-1.#c.e.a.#c1.e1.a1)[M],(A-2.A-1.#c.e.a.#c1.e1.a1)[M],(A-2.A-1.#c.e.a.#c1.e1.a1)[M],(A-2.A-1.#c.e.a.#c1.e1.a1)[M],(A-2.A-1.#c.e.a.#c1.e1.a1)[M],(A-2.A-1.#c.e.a.#c1.e1.a1)[M],(A-2.A-1.#c.e.a.#c1.e1.a1)[M],(A-2.A-1.#c.e.a.#c1.e1.a1)[M],(A-2.A-1.#c.e.a.#c1.e1.a1)[M],(A-2.A-1.#c.e.a.#c1.e1.a1)[M],(A-2.A-1.#c.e.a.#c1.e1.a1)[M],(A-2.A-1.#c.e.a.#c1.e1.a1)[M],(A-2.A-1.#c.e.a.#c1.e1.a1)[M],(A-2.A-1.#c.e.a.#c1.e1.a1)[M],(A-2.A-1.#c.e.a.#c1.e1.a1)[M],(A-2.A-1.#c.e.a.#c1.e1.a1)[M],(A-2.A-1.#c.e.a.#c1.e1.a1)[M],(A-2.A-1.#c.e.a.#c1.e1.a1)[M],(A-2.A-1.#c.e.a.#c1.e1.a1)[M],(A-2.A-1.#c.e.a.#c1.e1.a1)[M],(A-2.A-1.#c.e.a.#c1.e1.a1)[M],(A-2.A-1.#c.e.a.#c1.e1.a1)[M],(A-2.A-1.#c.e.a.#c1.e1.a1)[M],(A-2.A-1.#c.e.a.#c1.e1.a1)[M],(A-2.A-1.#c.e.a.#c1.e1.a1)[M],(A-2.A-1.#c.e.a.#c1.e1.a1)[M],(A-2.A-1.#c.e.a.#c1.e1.a1)[M],(A-2.A-1.#c.e.a.#c1.e1.a1)[M],(A-2.A-1.#c.e.a.#c1.e1.a1)[M],(A-2.A-1.#c.e.a.#c1.e1.a1)[M],(A-2.A-1.#c.e.a.#c1.e1.a1)[M],(A-2.A-1.#c.e.a.#c1.e1.a1)[M],(A-2.A-1.#c.e.a.#c1.e1.a1)[M],(A-2.A-1.#c.e.a.#c1.e1.a1)[M],(A-2.A-1.#c.e.a.#c1.e1.a1)[M],(A-2.A-1.#c.e.a.#c1.e1.a1)[M],(A-2.A-1.#c.e.a.#c1.e1.a1)[M],(A-2.A-1.#c.e.a.#c1.e1.a1)[M],(A-2.A-1.#c.e.a.#c1.e1.a1)[M],(A-2.A-1.#c.e.a.#c1.e1.a1)[M],(A-2.A-1.#c.e.a.#c1.e1.a1)[M],(A-2.A-1.#c.e.a.#c1.e1.a1)[M],(A-2.A-1.#c.e.a.#c1.e1.a1)[M],(A-2.A-1.#c.e.a.#c1.e1.a1)[M],(A-2.A-1.#c.e.a.#c1.e1.a1)[M],(A-2.A-1.#c.e.a.#c1.e1.a1)[M],(A-2.A-1.#c.e.a.#c1.e1.a1)[M],(A-2.A-1.#c.e.a.#c1.e1.a1)[M],(A-2.A-1.#c.e.a.#c1.e1.a1)[M],(A-2.A-1.#c.e.a.#c1.e1.a1)[M],(A-2.A-1.#c.e.a.#c1.e1.a1)[M],(A-2.A-1.#c.e.a.#c1.e1.a1)[M],(A-2.A-1.#c.e.a.#c1.e1.a1)[M],(A-2.A-1.#c.e.a.#c1.e1.a1)[M],(A-2.A-1.#c.e.a.#c1.e1.a1)[M],(A-2.A-1.#c.e.a.#c1.e1.a1)[M],(A-2.A-1.#c.e.a.#c1.e1.a1)[M],(A-2.A-1.#c.e.a.#c1.e1.a1)[M],(A-2.A-1.#c.e.a.#c1.e1.a1)[M],(A-2.A-1.#c.e.a.#c1.e1.a1)[M],(A-2.A-1.#c.e.a.#c1.e1.a1)[M],(A-2.A-1.#c.e.a.#c1.e1.a1)[M],(A-2.A-1.#c.e.a.#c1.e1.a1)[M],(A-2.A-1.#c.e.a.#c1.e1.a1)[M],(A-2.A-1.#c.e.a.#c1.e1.a1)[M],(A-2.A-1.#c.e.a.#c1.e1.a1)[M],(A-2.A-1.#c.e.a.#c1.e1.a1)[M],(A-2.A-1.#c.e.a.#c1.e1.a1)[M],(A-2.A-1.#c.e.a.#c1.e1.a1)[M],(A-2.A-1.#c.e.a.#c1.e1.a1)[M],(A-2.A-1.#c.e.a.#c1.e1.a1)[M],(A-2.A-1.#c.e.a.#c1.e1.a1)[M],(A-2.A-1.#c.e.a.#c1.e1.a1)[M],(A-2.A-1.#c.e.a.#c1.e1.a1)[M],(A-2.A-1.#c.e.a.#c1.e1.a1)[M],(A-2.A-1.#c.e.a.#c1.e1.a1)[M],(A-2.A-1.#c.e.a.#c1.e1.a1)[M],(A-2.A-1.#c.e.a.#c1.e1.a1)[M],(A-2.A-1.#c.e.a.#c1.e1.a1)[M],(A-2.A-1.#c.e.a.#c1.e1.a1)[M],(A-2.A-1.#c.e.a.#c1.e1.a1)[M],(A-2.A-1.#c.e.a.#c1.e1.a1)[M],(A-2.A-1.#c.e.a.#c1.e1.a1)[M],(A-2.A-1.#c.e.a.#c1.e1.a1)[M],(A-2.A-1.#c.e.a.#c1.e1.a1)[M],(A-2.A-1.#c.e.a.#c1.e1.a1)[M],(A-2.A-1.#c.e.a.#c1.e1.a1)[M],(A-2.A-1.#c.e.a.#c1.e1.a1)[M],(A-2.A-1.#c.e.a.#c1.e1.a1)[M],(A-2.A-1.#c.e.a.#c1.e1.a1)[M],(A-2.A-1.#c.e.a.#c1.e1.a1)[M],(A-2.A-1.#c.e.a.#c1.e1.a1)[M],(A-2.A-1.#c.e.a.#c1.e1.a1)[M],(A-2.A-1.#c.e.a.#c1.e1.a1)[M],(A-2.A-1.#c.e.a.#c1.e1.a1)[M],(A-2.A-1.#c.e.a.#c1.e1.a1)[M],(A-2.A-1.#c.e.a.#c1.e1.a1)[M],(A-2.A-1.#c.e.a.#c1.e1.a1)[M],(A-2.A-1.#c.e.a.#c1.e1.a1)[M],(A-2.A-1.#c.e.a.#c1.e1.a1)[M],(A-2.A-1.#c.e.a.#c1.e1.a1)[M],(A-2.A-1.#c.e.a.#c1.e1.a1)[M],(A-2.A-1.#c.e.a.#c1.e1.a1)[M],(A-2.A-1.#c.e.a.#c1.e1.a1)[M],(A-2.A-1.#c.e.a.#c1.e1.a1)[M],(A-2.A-1.#c.e.a.#c1.e1.a1)[M],(A-2.A-1.#c.e.a.#c1.e1.a1)[M],(A-2.A-1.#c.e.a.#c1.e1.a1)[M],(A-2.A-1.#c.e.a.#c1.e1.a1)[M],(A-2.A-1.#c.e.a.#c1.e1.a1)[M],(A-2.A-1.#c.e.a.#c1.e1.a1)[M],(A-2.A-1.#c.e.a.#c1.e1.a1)[M],(A-2.A-1.#c.e.a.#c1.e1.a1)[M],(A-2.A-1.#c.e.a.#c1.e1.a1)[M],(A-2.A-1.#c.e.a.#c1.e1.a1)[M],(A-2.A-1.#c.e.a.#c1.e1.a1)[M],(A-2.A-1.#c.e.a.#c1.e1.a1)[M],(A-2.A-1.#c.e.a.#c1.e1.a1)[M],(A-2.A-1.#c.e.a.#c1.e1.a1)[M],(A-2.A-1.#c.e.a.#c1.e1.a1)[M],(A-2.A-1.#c.e.a.#c1.e1.a1)[M],(A-2.A-1.#c.e.a.#c1.e1.a1)[M],(A-2.A-1.#c.e.a.#c1.e1.a1)[M],(A-2.A-1.#c.e.a.#c1.e1.a1)[M],(A-2.A-1.#c.e.a.#c1.e1.a1)[M],(A-2.A-1.#c.e.a.#c1.e1.a1)[M],(A-2.A-1.#c.e.a.#c1.e1.a1)[M],(A-2.A-1.#c.e.a.#c1.e1.a1)[M],(A-2.A-1.#c.e.a.#c1.e1.a1)[M],(A-2.A-1.#c.e.a.#c1.e1.a1)[M],(A-2.A-1.#c.e.a.#c1.e1.a1)[M],(A-2.A-1.#c.e.a.#c1.e1.a1)[M],(A-2.A-1.#c.e.a.#c1.e1.a1)[M],(A-2.A-1.#c.e.a.#c1.e1.a1)[M],(A-2.A-1.#c.e.a.#c1.e1.a1)[M],(A-2.A-1.#c.e.a.#c1.e1.a1)[M],(A-2.A-1.#c.e.a.#c1.e1.a1)[M],(A-2.A-1.#c.e.a.#c1.e1.a1)[M],(A-2.A-1.#c.e.a.#c1.e1.a1)[M],(A-2.A-1.#c.e.a.#c1.e1.a1)[M],(A-2.A-1.#c.e.a.#c1.e1.a1)[M],(A-2.A-1.#c.e.a.#c1.e1.a1)[M],(A-2.A-1.#c.e.a.#c1.e1.a1)[M],(A-2.A-1.#c.e.a.#c1.e1.a1)[M],(A-2.A-1.#c.e.a.#c1.e1.a1)[M],(A-2.A-1.#c.e.a.#c1.e1.a1)[M],(A-2.A-1.#c.e.a.#c1.e1.a1)[M],(A-2.A-1.#c.e.a.#c1.e1.a1)[M],(A-2.A-1.#c.e.a.#c1.e1.a1)[M],(A-2.A-1.#c.e.a.#c1.e1.a1)[M],(A-2.A-1.#c.e.a.#c1.e1.a1)[M],(A-2.A-1.#c.e.a.#c1.e1.a1)[M],(A-2.A-1.#c.e.a.#c1.e1.a1)[M],(A-2.A-1.#c.e.a.#c1.e1.a1)[M],(A-2.A-1.#c.e.a.#c1.e1.a1)[M],(A-2.A-1.#c.e.a.#c1.e1.a1)[M],(A-2.A-1.#c.e.a.#c1.e1.a1)[M],(A-2.A-1.#c.e.a.#c1.e1.a1)[M],(A-2.A-1.#c.e.a.#c1.e1.a1)[M],(A-2.A-1.#c.e.a.#c1.e1.a1)[M],(A-2.A-1.#c.e.a.#c1.e1.a1)[M],(A-2.A-1.#c.e.a.#c1.e1.a1)[M],(A-2.A-1.#c.e.a.#c1.e1.a1)[M],(A-2.A-1.#c.e.a.#c1.e1.a1)[M],(A-2.A-1.#c.e.a.#c1.e1.a1)[M],(A-2.A-1.#c.e.a.#c1.e1.a1)[M],(A-2.A-1.#c.e.a.#c1.e1.a1)[M],(A-2.A-1.#c.e.a.#c1.e1.a1)[M],(A-2.A-1.#c.e.a.#c1.e1.a1)[M],(A-2.A-1.#c.e.a.#c1.e1.a1)[M],(A-2.A-1.#c.e.a.#c1.e1.a1)[M],(A-2.A-1.#c.e.a.#c1.e1.a1)[M],(A-2.A-1.#c.e.a.#c1.e1.a1)[M],(A-2.A-1.#c.e.a.#c1.e1.a1)[M],(A-2.A-1.#c.e.a.#c1.e1.a1)[M],(A-2.A-1.#c.e.a.#c1.e1.a1)[M],(A-2.A-1.#c.e.a.#c1.e1.a1)[M],(A-2.A-1.#c.e.a.#c1.e1.a1)[M],(A-2.A-1.#c.e.a.#c1.e1.a1)[M],(A-2.A-1.#c.e.a.#c1.e1.a1)[M],(A-2.A-1.#c.e.a.#c1.e1.a1)[M],(A-2.A-1.#c.e.a.#c1.e1.a1)[M],(A-2.A-1.#c.e.a.#c1.e1.a1)[M],(A-2.A-1.#c.e.a.#c1.e1.a1)[M],(A-2.A-1.#c.e.a.#c1.e1.a1)[M],(A-2.A-1.#c.e.a.#c1.e1.a1)[M],(A-2.A-1.#c.e.a.#c1.e1.a1)[M],(A-2.A-1.#c.e.a.#c1.e1.a1)[M],(A-2.A-1.#c.e.a.#c1.e1.a1)[M],(A-2.A-1.#c.e.a.#c1.e1.a1)[M],(A-2.A-1.#c.e.a.#c1.e1.a1)[M],(A-2.A-1.#c.e.a.#c1.e1.a1)[M],(A-2.A-1.#c.e.a.#c1.e1.a1)[M],(A-2.A-1.#c.e.a.#c1.e1.a1)[M],(A-2.A-1.#c.e.a.#c1.e1.a1)[M],(A-2.A-1.#c.e.a.#c1.e1.a1)[M],(A-2.A-1.#c.e.a.#c1.e1.a1)[M],(A-2.A-1.#c.e.a.#c1.e1.a1)[M],(A-2.A-1.#c.e.a.#c1.e1.a1)[M],(A-2.A-1.#c.e.a.#c1.e1.a1)[M],(A-2.A-1.#c.e.a.#c1.e1.a1)[M],(A-2.A-1.#c.e.a.#c1.e1.a1)[M],(A-2.A-1.#c.e.a.#c1.e1.a1)[M],(A-2.A-1.#c.e.a.#c1.e1.a1)[M],(A-2.A-1.#c.e.a.#c1.e1.a1)[M],(A-2.A-1.#c.e.a.#c1.e1.a1)[M],(A-2.A-1.#c.e.a.#c1.e1.a1)[M],(A-2.A-1.#c.e.a.#c1.e1.a1)[M],(A-2.A-1.#c.e.a.#c1.e1.a1)[M],(A-2.A-1.#c.e.a.#c1.e1.a1)[M],(A-2.A-1.#c.e.a.#c1.e1.a1)[M],(A-2.A-1.#c.e.a.#c1.e1.a1)[M],(A-2.A-1.#c.e.a.#c1.e1.a1)[M],(A-2.A-1.#c.e.a.#c1.e1.a1)[M],(A-2.A-1.#c.e.a.#c1.e1.a1)[M],(A-2.A-1.#c.e.a.#c1.e1.a1)[M],(A-2.A-1.#c.e.a.#c1.e1.a1)[M],(A-2.A-1.#c.e.a.#c1.e1.a1)[M],(A-2.A-1.#c.e.a.#c1.e1.a1)[M],(A-2.A-1.#c.e.a.#c1.e1.a1)[M],(A-2.A-1.#c.e.a.#c1.e1.a1)[M],(A-2.A-1.#c.e.a.#c1.e1.a1)[M],(A-2.A-1.#c.e.a.#c1.e1.a1)[M],(A-2.A-1.#c.e.a.#c1.e1.a1)[M],(A-2.A-1.#c.e.a.#c1.e1.a1)[M],(A-2.A-1.#c.e.a.#c1.e1.a1)[M],(A-2.A-1.#c.e.a.#c1.e1.a1)[M],(A-2.A-1.#c.e.a.#c1.e1.a1)[M],(A-2.A-1.#c.e.a.#c1.e1.a1)[M],(A-2.A-1.#c.e.a.#c1.e1.a1)[M],(A-2.A-1.#c.e.a.#c1.e1.a1)[M],(A-2.A-1.#c.e.a.#c1.e1.a1)[M],(A-2.A-1.#c.e.a.#c1.e1.a1)[M],(A-2.A-1.#c.e.a.#c1.e1.a1)[M],(A-2.A-1.#c.e.a.#c1.e1.a1)[M],(A-2.A-1.#c.e.a.#c1.e1.a1)[M],(A-2.A-1.#c.e.a.#c1.e1.a1)[M],(A-2.A-1.#c.e.a.#c1.e1.a1)[M],(A-2.A-1.#c.e.a.#c1.e1.a1)[M],(A-2.A-1.#c.e.a.#c1.e1.a1)[M],(A-2.A-1.#c.e.a.#c1.e1.a1)[M],(A-2.A-1.#c.e.a.#c1.e1.a1)[M],(A-2.A-1.#c.e.a.#c1.e1.a1)[M],(A-2.A-1.#c.e.a.#c1.e1.a1)[M],(A-2.A-1.#c.e.a.#c1.e1.a1)[M],(A-2.A-1.#c.e.a.#c1.e1.a1)[M],(A-2.A-1.#c.e.a.#c1.e1.a1)[M],(A-2.A-1.#c.e.a.#c1.e1.a1)[M],(A-2.A-1.#c.e.a.#c1.e1.a1)[M],(A-2.A-1.#c.e.a.#c1.e1.a1)[M],(A-2.A-1.#c.e.a.#c1.e1.a1)[M],(A-2.A-1.#c.e.a.#c1.e1.a1)[M],(A-2.A-1.#c.e.a.#c1.e1.a1)[M],(A-2.A-1.#c.e.a.#c1.e1.a1)[M],(A-2.A-1.#c.e.a.#c1.e1.a1)[M],(A-2.A-1.#c.e.a.#c1.e1.a1)[M],(A-2.A-1.#c.e.a.#c1.e1.a1)[M],(A-2.A-1.#c.e.a.#c1.e1.a1)[M],(A-2.A-1.#c.e.a.#c1.e1.a1)[M],(A-2.A-1.#c.e.a.#c1.e1.a1)[M],(A-2.A-1.#c.e.a.#c1.e1.a1)[M],(A-2.A-1.#c.e.a.#c1.e1.a1)[M],(A-2.A-1.#c.e.a.#c1.e1.a1)[M],(A-2.A-1.#c.e.a.#c1.e1.a1)[M],(A-2.A-1.#c.e.a.#c1.e1.a1)[M],(A-2.A-1.#c.e.a.#c1.e1.a1)[M],(A-2.A-1.#c.e.a.#c1.e1.a1)[M],(A-2.A-1.#c.e.a.#c1.e1.a1)[M],(A-2.A-1.#c.e.a.#c1.e1.a1)[M],(A-2.A-1.#c.e.a.#c1.e1.a1)[M],(A-2.A-1.#c.e.a.#c1.e1.a1)[M],(A-2.A-1.#c.e.a.#c1.e1.a1)[M],(A-2.A-1.#c.e.a.#c1.e1.a1)[M],(A-2.A-1.#c.e.a.#c1.e1.a1)[M],(A-2.A-1.#c.e.a.#c1.e1.a1)[M],(A-2.A-1.#c.e.a.#c1.e1.a1)[M],(A-2.A-1.#c.e.a.#c1.e1.a1)[M],(A-2.A-1.#c.e.a.#c1.e1.a1)[M],(A-2.A-1.#c.e.a.#c1.e1.a1)[M],(A-2.A-1.#c.e.a.#c1.e1.a1)[M],(A-2.A-1.#c.e.a.#c1.e1.a1)[M],(A-2.A-1.#c.e.a.#c1.e1.a1)[M],(A-2.A-1.#c.e.a.#c1.e1.a1)[M],(A-2.A-1.#c.e.a.#c1.e1.a1)[M],(A-2.A-1.#c.e.a.#c1.e1.a1)[M],(A-2.A-1.#c.e.a.#c1.e1.a1)[M],(A-2.A-1.#c.e.a.#c1.e1.a1)[M],(A-2.A-1.#c.e.a.#c1.e1.a1)[M],(A-2.A-1.#c.e.a.#c1.e1.a1)[M],(A-2.A-1.#c.e.a.#c1.e1.a1)[M],(A-2.A-1.#c.e.a.#c1.e1.a1)[M],(A-2.A-1.#c.e.a.#c1.e1.a1)[M],(A-2.A-1.#c.e.a.#c1.e1.a1)[M],(A-2.A-1.#c.e.a.#c1.e1.a1)[M],(A-2.A-1.#c.e.a.#c1.e1.a1)[M],(A-2.A-1.#c.e.a.#c1.e1.a1)[M],(A-2.A-1.#c.e.a.#c1.e1.a1)[M],(A-2.A-1.#c.e.a.#c1.e1.a1)[M],(A-2.A-1.#c.e.a.#c1.e1.a1)[M],(A-2.A-1.#c.e.a.#c1.e1.a1)[M],(A-2.A-1.#c.e.a.#c1.e1.a1)[M],(A-2.A-1.#c.e.a.#c1.e1.a1)[M],(A-2.A-1.#c.e.a.#c1.e1.a1)[M],(A-2.A-1.#c.e.a.#c1.e1.a1)[M],(A-2.A-1.#c.e.a.#c1.e1.a1)[M],(A-2.A-1.#c.e.a.#c1.e1.a1)[M],(A-2.A-1.#c.e.a.#c1.e1.a1)[M],(A-2.A-1.#c.e.a.#c1.e1.a1)[M],(A-2.A-1.#c.e.a.#c1.e1.a1)[M],(A-2.A-1.#c.e.a.#c1.e1.a1)[M],(A-2.A-1.#c.e.a.#c1.e1.a1)[M],(A-2.A-1.#c.e.a.#c1.e1.a1)[M],(A-2.A-1.#c.e.a.#c1.e1.a1)[M],(A-2.A-1.#c.e.a.#c1.e1.a1)[M],(A-2.A-1.#c.e.a.#c1.e1.a1)[M],(A-2.A-1.#c.e.a.#c1.e1.a1)[M],(A-2.A-1.#c.e.a.#c1.e1.a1)[M],(A-2.A-1.#c.e.a.#c1.e1.a1)[M],(A-2.A-1.#c.e.a.#c1.e1.a1)[M],(A-2.A-1.#c.e.a.#c1.e1.a1)[M],(A-2.A-1.#c.e.a.#c1.e1.a1)[M],(A-2.A-1.#c.e.a.#c1.e1.a1)[M],(A-2.A-1.#c.e.a.#c1.e1.a1)[M],(A-2.A-1.#c.e.a.#c1.e1.a1)[M],(A-2.A-1.#c.e.a.#c1.e1.a1)[M],(A-2.A-1.#c.e.a.#c1.e1.a1)[M],(A-2.A-1.#c.e.a.#c1.e1.a1)[M],(A-2.A-1.#c.e.a.#c1.e1.a1)[M],(A-2.A-1.#c.e.a.#c1.e1.a1)[M],(A-2.A-1.#c.e.a.#c1.e1.a1)[M],(A-2.A-1.#c.e.a.#c1.e1.a1)[M],(A-2.A-1.#c.e.a.#c1.e1.a1)[M],(A-2.A-1.#c.e.a.#c1.e1.a1)[M],(A-2.A-1.#c.e.a.#c1.e1.a1)[M],(A-2.A-1.#c.e.a.#c1.e1.a1)[M],(A-2.A-1.#c.e.a.#c1.e1.a1)[M],(A-2.A-1.#c.e.a.#c1.e1.a1)[M],(A-2.A-1.#c.e.a.#c1.e1.a1)[M],(A-2.A-1.#c.e.a.#c1.e1.a1)[M],(A-2.A-1.#c.e.a.#c1.e1.a1)[M],(A-2.A-1.#c.e.a.#c1.e1.a1)[M],(A-2.A-1.#c.e.a.#c1.e1.a1)[M],(A-2.A-1.#c.e.a.#c1.e1.a1)[M],(A-2.A-1.#c.e.a.#c1.e1.a1)[M],(A-2.A-1.#c.e.a.#c1.e1.a1)[M],(A-2.A-1.#c.e.a.#c1.e1.a1)[M],(A-2.A-1.#c.e.a.#c1.e1.a1)[M],(A-2.A-1.#c.e.a.#c1.e1.a1)[M],(A-2.A-1.#c.e.a.#c1.e1.a1)[M],(A-2.A-1.#c.e.a.#c1.e1.a1)[M],(A-2.A-1.#c.e.a.#c1.e1.a1)[M],(A-2.A-1.#c.e.a.#c1.e1.a1)[M],(A-2.A-1.#c.e.a.#c1.e1.a1)[M],(A-2.A-1.#c.e.a.#c1.e1.a1)[M],(A-2.A-1.#c.e.a.#c1.e1.a1)[M],(A-2.A-1.#c.e.a.#c1.e1.a1)[M],(A-2.A-1.#c.e.a.#c1.e1.a1)[M],(A-2.A-1.#c.e.a.#c1.e1.a1)[M],(A-2.A-1.#c.e.a.#c1.e1.a1)[M],(A-2.A-1.#c.e.a.#c1.e1.a1)[M],(A-2.A-1.#c.e.a.#c1.e1.a1)[M],(A-2.A-1.#c.e.a.#c1.e1.a1)[M],(A-2.A-1.#c.e.a.#c1.e1.a1)[M],(A-2.A-1.#c.e.a.#c1.e1.a1)[M],(A-2.A-1.#c.e.a.#c1.e1.a1)[M],(A-2.A-1.#c.e.a.#c1.e1.a1)[M],(A-2.A-1.#c.e.a.#c1.e1.a1)[M],(A-2.A-1.#c.e.a.#c1.e1.a1)[M],(A-2.A-1.#c.e.a.#c1.e1.a1)[M],(A-2.A-1.#c.e.a.#c1.e1.a1)[M],(A-2.A-1.#c.e.a.#c1.e1.a1)[M],(A-2.A-1.#c.e.a.#c1.e1.a1)[M],(A-2.A-1.#c.e.a.#c1.e1.a1)[M],(A-2.A-1.#c.e.a.#c1.e1.a1)[M],(A-2.A-1.#c.e.a.#c1.e1.a1)[M],(A-2.A-1.#c.e.a.#c1.e1.a1)[M],(A-2.A-1.#c.e.a.#c1.e1.a1)[M],(A-2.A-1.#c.e.a.#c1.e1.a1)[M],(A-2.A-1.#c.e.a.#c1.e1.a1)[M],(A-2.A-1.#c.e.a.#c1.e1.a1)[M],(A-2.A-1.#c.e.a.#c1.e1.a1)[M],(A-2.A-1.#c.e.a.#c1.e1.a1)[M],(A-2.A-1.#c.e.a.#c1.e1.a1)[M],(A-2.A-1.#c.e.a.#c1.e1.a1)[M],(A-2.A-1.#c.e.a.#c1.e1.a1)[M],(A-2.A-1.#c.e.a.#c1.e1.a1)[M],(A-2.A-1.#c.e.a.#c1.e1.a1)[M],(A-2.A-1.#c.e.a.#c1.e1.a1)[M],(A-2.A-1.#c.e.a.#c1.e1.a1)[M],(A-2.A-1.#c.e.a.#c1.e1.a1)[M],(A-2.A-1.#c.e.a.#c1.e1.a1)[M],(A-2.A-1.#c.e.a.#c1.e1.a1)[M],(A-2.A-1.#c.e.a.#c1.e1.a1)[M],(A-2.A-1.#c.e.a.#c1.e1.a1)[M],(A-2.A-1.#c.e.a.#c1.e1.a1)[M],(A-2.A-1.#c.e.a.#c1.e1.a1)[M],(A-2.A-1.#c.e.a.#c1.e1.a1)[M],(A-2.A-1.#c.e.a.#c1.e1.a1)[M],(A-2.A-1.#c.e.a.#c1.e1.a1)[M],(A-2.A-1.#c.e.a.#c1.e1.a1)[M],(A-2.A-1.#c.e.a.#c1.e1.a1)[M],(A-2.A-1.#c.e.a.#c1.e1.a1)[M],(A-2.A-1.#c.e.a.#c1.e1.a1)[M],(A-2.A-1.#c.e.a.#c1.e1.a1)[M],(A-2.A-1.#c.e.a.#c1.e1.a1)[M],(A-2.A-1.#c.e.a.#c1.e1.a1)[M],(A-2.A-1.#c.e.a.#c1.e1.a1)[M],(A-2.A-1.#c.e.a.#c1.e1.a1)[M],(A-2.A-1.#c.e.a.#c1.e1.a1)[M],(A-2.A-1.#c.e.a.#c1.e1.a1)[M],(A-2.A-1.#c.e.a.#c1.e1.a1)[M],(A-2.A-1.#c.e.a.#c1.e1.a1)[M],(A-2.A-1.#c.e.a.#c1.e1.a1)[M],(A-2.A-1.#c.e.a.#c1.e1.a1)[M],(A-2.A-1.#c.e.a.#c1.e1.a1)[M],(A-2.A-1.#c.e.a.#c1.e1.a1)[M],(A-2.A-1.#c.e.a.#c1.e1.a1)[M],(A-2.A-1.#c.e.a.#c1.e1.a1)[M],(A-2.A-1.#c.e.a.#c1.e1.a1)[M],(A-2.A-1.#c.e.a.#c1.e1.a1)[M],(A-2.A-1.#c.e.a.#c1.e1.a1)[M],(A-2.A-1.#c.e.a.#c1.e1.a1)[M],(A-2.A-1.#c.e.a.#c1.e1.a1)[M],(A-2.A-1.#c.e.a.#c1.e1.a1)[M],(A-2.A-1.#c.e.a.#c1.e1.a1)[M],(A-2.A-1.#c.e.a.#c1.e1.a1)[M],(A-2.A-1.#c.e.a.#c1.e1.a1)[M],(A-2.A-1.#c.e.a.#c1.e1.a1)[M],(A-2.A-1.#c.e.a.#c1.e1.a1)[M],(A-2.A-1.#c.e.a.#c1.e1.a1)[M],(A-2.A-1.#c.e.a.#c1.e1.a1)[M],(A-2.A-1.#c.e.a.#c1.e1.a1)[M],(A-2.A-1.#c.e.a.#c1.e1.a1)[M],(A-2.A-1.#c.e.a.#c1.e1.a1)[M],(A-2.A-1.#c.e.a.#c1.e1.a1)[M],(A-2.A-1.#c.e.a.#c1.e1.a1)[M],(A-2.A-1.#c.e.a.#c1.e1.a1)[M],(A-2.A-1.#c.e.a.#c1.e1.a1)[M],(A-2.A-1.#c.e.a.#c1.e1.a1)[M],(A-2.A-1.#c.e.a.#c1.e1.a1)[M],(A-2.A-1.#c.e.a.#c1.e1.a1)[M],(A-2.A-1.#c.e.a.#c1.e1.a1)[M],(A-2.A-1.#c.e.a.#c1.e1.a1)[M],(A-2.A-1.#c.e.a.#c1.e1.a1)[M],(A-2.A-1.#c.e.a.#c1.e1.a1)[M],(A-2.A-1.#c.e.a.#c1.e1.a1)[M],(A-2.A-1.#c.e.a.#c1.e1.a1)[M],(A-2.A-1.#c.e.a.#c1.e1.a1)[M],(A-2.A-1.#c.e.a.#c1.e1.a1)[M],(A-2.A-1.#c.e.a.#c1.e1.a1)[M],(A-2.A-1.#c.e.a.#c1.e1.a1)[M],(A-2.A-1.#c.e.a.#c1.e1.a1)[M],(A-2.A-1.#c.e.a.#c1.e1.a1)[M],(A-2.A-1.#c.e.a.#c1.e1.a1)[M],(A-2.A-1.#c.e.a.#c1.e1.a1)[M],(A-2.A-1.#c.e.a.#c1.e1.a1)[M],(A-2.A-1.#c.e.a.#c1.e1.a1)[M],(A-2.A-1.#c.e.a.#c1.e1.a1)[M],(A-2.A-1.#c.e.a.#c1.e1.a1)[M],(A-2.A-1.#c.e.a.#c1.e1.a1)[M],(A-2.A-1.#c.e.a.#c1.e1.a1)[M],(A-2.A-1.#c.e.a.#c1.e1.a1)[M],(A-2.A-1.#c.e.a.#c1.e1.a1)[M],(A-2.A-1.#c.e.a.#c1.e1.a1)[M],(A-2.A-1.#c.e.a.#c1.e1.a1)[M],(A-2.A-1.#c.e.a.#c1.e1.a1)[M],(A-2.A-1.#c.e.a.#c1.e1.a1)[M],(A-2.A-1.#c.e.a.#c1.e1.a1)[M],(A-2.A-1.#c.e.a.#c1.e1.a1)[M],(A-2.A-1.#c.e.a.#c1.e1.a1)[M],(A-2.A-1.#c.e.a.#c1.e1.a1)[M],(A-2.A-1.#c.e.a.#c1.e1.a1)[M],(A-2.A-1.#c.e.a.#c1.e1.a1)[M],(A-2.A-1.#c.e.a.#c1.e1.a1)[M],(A-2.A-1.#c.e.a.#c1.e1.a1)[M],(A-2.A-1.#c.e.a.#c1.e1.a1)[M],(A-2.A-1.#c.e.a.#c1.e1.a1)[M],(A-2.A-1.#c.e.a.#c1.e1.a1)[M],(A-2.A-1.#c.e.a.#c1.e1.a1)[M],(A-2.A-1.#c.e.a.#c1.e1.a1)[M],(A-2.A-1.#c.e.a.#c1.e1.a1)[M],(A-2.A-1.#c.e.a.#c1.e1.a1)[M],(A-2.A-1.#c.e.a.#c1.e1.a1)[M],(A-2.A-1.#c.e.a.#c1.e1.a1)[M],(A-2.A-1.#c.e.a.#c1.e1.a1)[M],(A-2.A-1.#c.e.a.#c1.e1.a1)[M],(A-2.A-1.#c.e.a.#c1.e1.a1)[M],(A-2.A-1.#c.e.a.#c1.e1.a1)[M],(A-2.A-1.#c.e.a.#c1.e1.a1)[M],(A-2.A-1.#c.e.a.#c1.e1.a1)[M],(A-2.A-1.#c.e.a.#c1.e1.a1)[M],(A-2.A-1.#c.e.a.#c1.e1.a1)[M],(A-2.A-1.#c.e.a.#c1.e1.a1)[M],(A-2.A-1.#c.e.a.#c1.e1.a1)[M],(A-2.A-1.#c.e.a.#c1.e1.a1)[M],(A-2.A-1.#c.e.a.#c1.e1.a1)[M],(A-2.A-1.#c.e.a.#c1.e1.a1)[M],(A-2.A-1.#c.e.a.#c1.e1.a1)[M],(A-2.A-1.#c.e.a.#c1.e1.a1)[M],(A-2.A-1.#c.e.a.#c1.e1.a1)[M],(A-2.A-1.#c.e.a.#c1.e1.a1)[M],(A-2.A-1.#c.e.a.#c1.e1.a1)[M],(A-2.A-1.#c.e.a.#c1.e1.a1)[M],(A-2.A-1.#c.e.a.#c1.e1.a1)[M],(A-2.A-1.#c.e.a.#c1.e1.a1)[M],(A-2.A-1.#c.e.a.#c1.e1.a1)[M],(A-2.A-1.#c.e.a.#c1.e1.a1)[M],(A-2.A-1.#c.e.a.#c1.e1.a1)[M],(A-2.A-1.#c.e.a.#c1.e1.a1)[M],(A-2.A-1.#c.e.a.#c1.e1.a1)[M],(A-2.A-1.#c.e.a.#c1.e1.a1)[M],(A-2.A-1.#c.e.a.#c1.e1.a1)[M],(A-2.A-1.#c.e.a.#c1.e1.a1)[M],(A-2.A-1.#c.e.a.#c1.e1.a1)[M],(A-2.A-1.#c.e.a.#c1.e1.a1)[M],(A-2.A-1.#c.e.a.#c1.e1.a1)[M],(A-2.A-1.#c.e.a.#c1.e1.a1)[M],(A-2.A-1.#c.e.a.#c1.e1.a1)[M],(A-2.A-1.#c.e.a.#c1.e1.a1)[M],(A-2.A-1.#c.e.a.#c1.e1.a1)[M],(A-2.A-1.#c.e.a.#c1.e1.a1)[M],(A-2.A-1.#c.e.a.#c1.e1.a1)[M],(A-2.A-1.#c.e.a.#c1.e1.a1)[M],(A-2.A-1.#c.e.a.#c1.e1.a1)[M],(A-2.A-1.#c.e.a.#c1.e1.a1)[M],(A-2.A-1.#c.e.a.#c1.e1.a1)[M],(A-2.A-1.#c.e.a.#c1.e1.a1)[M],(A-2.A-1.#c.e.a.#c1.e1.a1)[M],(A-2.A-1.#c.e.a.#c1.e1.a1)[M],(A-2.A-1.#c.e.a.#c1.e1.a1)[M],(A-2.A-1.#c.e.a.#c1.e1.a1)[M],(A-2.A-1.#c.e.a.#c1.e1.a1)[M],(A-2.A-1.#c.e.a.#c1.e1.a1)[M],(A-2.A-1.#c.e.a.#c1.e1.a1)[M],(A-2.A-1.#c.e.a.#c1.e1.a1)[M],(A-2.A-1.#c.e.a.#c1.e1.a1)[M],(A-2.A-1.#c.e.a.#c1.e1.a1)[M],(A-2.A-1.#c.e.a.#c1.e1.a1)[M],(A-2.A-1.#c.e.a.#c1.e1.a1)[M],(A-2.A-1.#c.e.a.#c1.e1.a1)[M],(A-2.A-1.#c.e.a.#c1.e1.a1)[M],(A-2.A-1.#c.e.a.#c1.e1.a1)[M],(A-2.A-1.#c.e.a.#c1.e1.a1)[M],(A-2.A-1.#c.e.a.#c1.e1.a1)[M],(A-2.A-1.#c.e.a.#c1.e1.a1)[M],(A-2.A-1.#c.e.a.#c1.e1.a1)[M],(A-2.A-1.#c.e.a.#c1.e1.a1)[M],(A-2.A-1.#c.e.a.#c1.e1.a1)[M],(A-2.A-1.#c.e.a.#c1.e1.a1)[M],(A-2.A-1.#c.e.a.#c1.e1.a1)[M],(A-2.A-1.#c.e.a.#c1.e1.a1)[M],(A-2.A-1.#c.e.a.#c1.e1.a1)[M],(A-2.A-1.#c.e.a.#c1.e1.a1)[M],(A-2.A-1.#c.e.a.#c1.e1.a1)[M],(A-2.A-1.#c.e.a.#c1.e1.a1)[M],(A-2.A-1.#c.e.a.#c1.e1.a1)[M],(A-2.A-1.#c.e.a.#c1.e1.a1)[M],(A-2.A-1.#c.e.a.#c1.e1.a1)[M],(A-2.A-1.#c.e.a.#c1.e1.a1)[M],(A-2.A-1.#c.e.a.#c1.e1.a1)[M],(A-2.A-1.#c.e.a.#c1.e1.a1)[M],(A-2.A-1.#c.e.a.#c1.e1.a1)[M],(A-2.A-1.#c.e.a.#c1.e1.a1)[M],(A-2.A-1.#c.e.a.#c1.e1.a1)[M],(A-2.A-1.#c.e.a.#c1.e1.a1)[M],(A-2.A-1.#c.e.a.#c1.e1.a1)[M],(A-2.A-1.#c.e.a.#c1.e1.a1)[M],(A-2.A-1.#c.e.a.#c1.e1.a1)[M],(A-2.A-1.#c.e.a.#c1.e1.a1)[M],(A-2.A-1.#c.e.a.#c1.e1.a1)[M],(A-2.A-1.#c.e.a.#c1.e1.a1)[M],(A-2.A-1.#c.e.a.#c1.e1.a1)[M],(A-2.A-1.#c.e.a.#c1.e1.a1)[M],(A-2.A-1.#c.e.a.#c1.e1.a1)[M],(A-2.A-1.#c.e.a.#c1.e1.a1)[M],(A-2.A-1.#c.e.a.#c1.e1.a1)[M],(A-2.A-1.#c.e.a.#c1.e1.a1)[M],(A-2.A-1.#c.e.a.#c1.e1.a1)[M],(A-2.A-1.#c.e.a.#c1.e1.a1)[M],(A-2.A-1.#c.e.a.#c1.e1.a1)[M],(A-2.A-1.#c.e.a.#c1.e1.a1)[M],(A-2.A-1.#c.e.a.#c1.e1.a1)[M],(A-2.A-1.#c.e.a.#c1.e1.a1)[M],(A-2.A-1.#c.e.a.#c1.e1.a1)[M],(A-2.A-1.#c.e.a.#c1.e1.a1)[M],(A-2.A-1.#c.e.a.#c1.e1.a1)[M],(A-2.A-1.#c.e.a.#c1.e1.a1)[M],(A-2.A-1.#c.e.a.#c1.e1.a1)[M],(A-2.A-1.#c.e.a.#c1.e1.a1)[M],(A-2.A-1.#c.e.a.#c1.e1.a1)[M],(A-2.A-1.#c.e.a.#c1.e1.a1)[M],(A-2.A-1.#c.e.a.#c1.e1.a1)[M],(A-2.A-1.#c.e.a.#c1.e1.a1)[M],(A-2.A-1.#c.e.a.#c1.e1.a1)[M],(A-2.A-1.#c.e.a.#c1.e1.a1)[M],(A-2.A-1.#c.e.a.#c1.e1.a1)[M],(A-2.A-1.#c.e.a.#c1.e1.a1)[M],(A-2.A-1.#c.e.a.#c1.e1.a1)[M],(A-2.A-1.#c.e.a.#c1.e1.a1)[M],(A-2.A-1.#c.e.a.#c1.e1.a1)[M],(A-2.A-1.#c.e.a.#c1.e1.a1)[M],(A-2.A-1.#c.e.a.#c1.e1.a1)[M],(A-2.A-1.#c.e.a.#c1.e1.a1)[M],(A-2.A-1.#c.e.a.#c1.e1.a1)[M],(A-2.A-1.#c.e.a.#c1.e1.a1)[M],(A-2.A-1.#c.e.a.#c1.e1.a1)[M],(A-2.A-1.#c.e.a.#c1.e1.a1)[M],(A-2.A-1.#c.e.a.#c1.e1.a1)[M],(A-2.A-1.#c.e.a.#c1.e1.a1)[M],(A-2.A-1.#c.e.a.#c1.e1.a1)[M],(A-2.A-1.#c.e.a.#c1.e1.a1)[M],(A-2.A-1.#c.e.a.#c1.e1.a1)[M],(A-2.A-1.#c.e.a.#c1.e1.a1)[M],(A-2.A-1.#c.e.a.#c1.e1.a1)[M],(A-2.A-1.#c.e.a.#c1.e1.a1)[M],(A-2.A-1.#c.e.a.#c1.e1.a1)[M],(A-2.A-1.#c.e.a.#c1.e1.a1)[M],(A-2.A-1.#c.e.a.#c1.e1.a1)[M],(A-2.A-1.#c.e.a.#c1.e1.a1)[M],(A-2.A-1.#c.e.a.#c1.e1.a1)[M],(A-2.A-1.#c.e.a.#c1.e1.a1)[M],(A-2.A-1.#c.e.a.#c1.e1.a1)[M],(A-2.A-1.#c.e.a.#c1.e1.a1)[M],(A-2.A-1.#c.e.a.#c1.e1.a1)[M],(A-2.A-1.#c.e.a.#c1.e1.a1)[M],(A-2.A-1.#c.e.a.#c1.e1.a1)[M],(A-2.A-1.#c.e.a.#c1.e1.a1)[M],(A-2.A-1.#c.e.a.#c1.e1.a1)[M],(A-2.A-1.#c.e.a.#c1.e1.a1)[M],(A-2.A-1.#c.e.a.#c1.e1.a1)[M],(A-2.A-1.#c.e.a.#c1.e1.a1)[M],(A-2.A-1.#c.e.a.#c1.e1.a1)[M],(A-2.A-1.#c.e.a.#c1.e1.a1)[M],(A-2.A-1.#c.e.a.#c1.e1.a1)[M],(A-2.A-1.#c.e.a.#c1.e1.a1)[M],(A-2.A-1.#c.e.a.#c1.e1.a1)[M],(A-2.A-1.#c.e.a.#c1.e1.a1)[M],(A-2.A-1.#c.e.a.#c1.e1.a1)[M],(A-2.A-1.#c.e.a.#c1.e1.a1)[M],(A-2.A-1.#c.e.a.#c1.e1.a1)[M],(A-2.A-1.#c.e.a.#c1.e1.a1)[M],(A-2.A-1.#c.e.a.#c1.e1.a1)[M],(A-2.A-1.#c.e.a.#c1.e1.a1)[M],(A-2.A-1.#c.e.a.#c1.e1.a1)[M],(A-2.A-1.#c.e.a.#c1.e1.a1)[M],(A-2.A-1.#c.e.a.#c1.e1.a1)[M],(A-2.A-1.#c.e.a.#c1.e1.a1)[M],(A-2.A-1.#c.e.a.#c1.e1.a1)[M],(A-2.A-1.#c.e.a.#c1.e1.a1)[M],(A-2.A-1.#c.e.a.#c1.e1.a1)[M],(A-2.A-1.#c.e.a.#c1.e1.a1)[M],(A-2.A-1.#c.e.a.#c1.e1.a1)[M],(A-2.A-1.#c.e.a.#c1.e1.a1)[M],(A-2.A-1.#c.e.a.#c1.e1.a1)[M],(A-2.A-1.#c.e.a.#c1.e1.a1)[M],(A-2.A-1.#c.e.a.#c1.e1.a1)[M],(A-2.A-1.#c.e.a.#c1.e1.a1)[M],(A-2.A-1.#c.e.a.#c1.e1.a1)[M],(A-2.A-1.#c.e.a.#c1.e1.a1)[M],(A-2.A-1.#c.e.a.#c1.e1.a1)[M],(A-2.A-1.#c.e.a.#c1.e1.a1)[M],(A-2.A-1.#c.e.a.#c1.e1.a1)[M],(A-2.A-1.#c.e.a.#c1.e1.a1)[M],(A-2.A-1.#c.e.a.#c1.e1.a1)[M],(A-2.A-1.#c.e.a.#c1.e1.a1)[M],(A-2.A-1.#c.e.a.#c1.e1.a1)[M],(A-2.A-1.#c.e.a.#c1.e1.a1)[M],(A-2.A-1.#c.e.a.#c1.e1.a1)[M],(A-2.A-1.#c.e.a.#c1.e1.a1)[M],(A-2.A-1.#c.e.a.#c1.e1.a1)[M],(A-2.A-1.#c.e.a.#c1.e1.a1)[M],(A-2.A-1.#c.e.a.#c1.e1.a1)[M],(A-2.A-1.#c.e.a.#c1.e1.a1)[M],(A-2.A-1.#c.e.a.#c1.e1.a1)[M],(A-2.A-1.#c.e.a.#c1.e1.a1)[M],(A-2.A-1.#c.e.a.#c1.e1.a1)[M],(A-2.A-1.#c.e.a.#c1.e1.a1)[M],(A-2.A-1.#c.e.a.#c1.e1.a1)[M],(A-2.A-1.#c.e.a.#c1.e1.a1)[M],(A-2.A-1.#c.e.a.#c1.e1.a1)[M],(A-2.A-1.#c.e.a.#c1.e1.a1)[M],(A-2.A-1.#c.e.a.#c1.e1.a1)[M],(A-2.A-1.#c.e.a.#c1.e1.a1)[M],(A-2.A-1.#c.e.a.#c1.e1.a1)[M],(A-2.A-1.#c.e.a.#c1.e1.a1)[M],(A-2.A-1.#c.e.a.#c1.e1.a1)[M],(A-2.A-1.#c.e.a.#c1.e1.a1)[M],(A-2.A-1.#c.e.a.#c1.e1.a1)[M],(A-2.A-1.#c.e.a.#c1.e1.a1)[M],(A-2.A-1.#c.e.a.#c1.e1.a1)[M],(A-2.A-1.#c.e.a.#c1.e1.a1)[M],(A-2.A-1.#c.e.a.#c1.e1.a1)[M],(A-2.A-1.#c.e.a.#c1.e1.a1)[M],(A-2.A-1.#c.e.a.#c1.e1.a1)[M],(A-2.A-1.#c.e.a.#c1.e1.a1)[M],(A-2.A-1.#c.e.a.#c1.e1.a1)[M],(A-2.A-1.#c.e.a.#c1.e1.a1)[M],(A-2.A-1.#c.e.a.#c1.e1.a1)[M],(A-2.A-1.#c.e.a.#c1.e1.a1)[M],(A-2.A-1.#c.e.a.#c1.e1.a1)[M],(A-2.A-1.#c.e.a.#c1.e1.a1)[M],(A-2.A-1.#c.e.a.#c1.e1.a1)[M],(A-2.A-1.#c.e.a.#c1.e1.a1)[M],(A-2.A-1.#c.e.a.#c1.e1.a1)[M],(A-2.A-1.#c.e.a.#c1.e1.a1)[M],(A-2.A-1.#c.e.a.#c1.e1.a1)[M],(A-2.A-1.#c.e.a.#c1.e1.a1)[M],(A-2.A-1.#c.e.a.#c1.e1.a1)[M],(A-2.A-1.#c.e.a.#c1.e1.a1)[M],(A-2.A-1.#c.e.a.#c1.e1.a1)[M],(A-2.A-1.#c.e.a.#c1.e1.a1)[M],(A-2.A-1.#c.e.a.#c1.e1.a1)[M],(A-2.A-1.#c.e.a.#c1.e1.a1)[M],(A-2.A-1.#c.e.a.#c1.e1.a1)[M],(A-2.A-1.#c.e.a.#c1.e1.a1)[M],(A-2.A-1.#c.e.a.#c1.e1.a1)[M],(A-2.A-1.#c.e.a.#c1.e1.a1)[M],(A-2.A-1.#c.e.a.#c1.e1.a1)[M],(A-2.A-1.#c.e.a.#c1.e1.a1)[M],(A-2.A-1.#c.e.a.#c1.e1.a1)[M],(A-2.A-1.#c.e.a.#c1.e1.a1)[M],(A-2.A-1.#c.e.a.#c1.e1.a1)[M],(A-2.A-1.#c.e.a.#c1.e1.a1)[M],(A-2.A-1.#c.e.a.#c1.e1.a1)[M],(A-2.A-1.#c.e.a.#c1.e1.a1)[M],(A-2.A-1.#c.e.a.#c1.e1.a1)[M],(A-2.A-1.#c.e.a.#c1.e1.a1)[M],(A-2.A-1.#c.e.a.#c1.e1.a1)[M],(A-2.A-1.#c.e.a.#c1.e1.a1)[M],(A-2.A-1.#c.e.a.#c1.e1.a1)[M],(A-2.A-1.#c.e.a.#c1.e1.a1)[M],(A-2.A-1.#c.e.a.#c1.e1.a1)[M],(A-2.A-1.#c.e.a.#c1.e1.a1)[M],(A-2.A-1.#c.e.a.#c1.e1.a1)[M],(A-2.A-1.#c.e.a.#c1.e1.a1)[M],(A-2.A-1.#c.e.a.#c1.e1.a1)[M],(A-2.A-1.#c.e.a.#c1.e1.a1)[M],(A-2.A-1.#c.e.a.#c1.e1.a1)[M],(A-2.A-1.#c.e.a.#c1.e1.a1)[M],(A-2.A-1.#c.e.a.#c1.e1.a1)[M],(A-2.A-1.#c.e.a.#c1.e1.a1)[M],(A-2.A-1.#c.e.a.#c1.e1.a1)[M],(A-2.A-1.#c.e.a.#c1.e1.a1)[M],(A-2.A-1.#c.e.a.#c1.e1.a1)[M],(A-2.A-1.#c.e.a.#c1.e1.a1)[M],(A-2.A-1.#c.e.a.#c1.e1.a1)[M],(A-2.A-1.#c.e.a.#c1.e1.a1)[M],(A-2.A-1.#c.e.a.#c1.e1.a1)[M],(A-2.A-1.#c.e.a.#c1.e1.a1)[M],(A-2.A-1.#c.e.a.#c1.e1.a1)[M],(A-2.A-1.#c.e.a.#c1.e1.a1)[M],(A-2.A-1.#c.e.a.#c1.e1.a1)[M],(A-2.A-1.#c.e.a.#c1.e1.a1)[M],(A-2.A-1.#c.e.a.#c1.e1.a1)[M],(A-2.A-1.#c.e.a.#c1.e1.a1)[M],(A-2.A-1.#c.e.a.#c1.e1.a1)[M],(A-2.A-1.#c.e.a.#c1.e1.a1)[M],(A-2.A-1.#c.e.a.#c1.e1.a1)[M],(A-2.A-1.#c.e.a.#c1.e1.a1)[M],(A-2.A-1.#c.e.a.#c1.e1.a1)[M],(A-2.A-1.#c.e.a.#c1.e1.a1)[M],(A-2.A-1.#c.e.a.#c1.e1.a1)[M],(A-2.A-1.#c.e.a.#c1.e1.a1)[M],(A-2.A-1.#c.e.a.#c1.e1.a1)[M],(A-2.A-1.#c.e.a.#c1.e1.a1)[M],(A-2.A-1.#c.e.a.#c1.e1.a1)[M],(A-2.A-1.#c.e.a.#c1.e1.a1)[M],(A-2.A-1.#c.e.a.#c1.e1.a1)[M],(A-2.A-1.#c.e.a.#c1.e1.a1)[M],(A-2.A-1.#c.e.a.#c1.e1.a1)[M],(A-2.A-1.#c.e.a.#c1.e1.a1)[M],(A-2.A-1.#c.e.a.#c1.e1.a1)[M],(A-2.A-1.#c.e.a.#c1.e1.a1)[M],(A-2.A-1.#c.e.a.#c1.e1.a1)[M],(A-2.A-1.#c.e.a.#c1.e1.a1)[M],(A-2.A-1.#c.e.a.#c1.e1.a1)[M],(A-2.A-1.#c.e.a.#c1.e1.a1)[M],(A-2.A-1.#c.e.a.#c1.e1.a1)[M],(A-2.A-1.#c.e.a.#c1.e1.a1)[M],(A-2.A-1.#c.e.a.#c1.e1.a1)[M],(A-2.A-1.#c.e.a.#c1.e1.a1)[M],(A-2.A-1.#c.e.a.#c1.e1.a1)[M],(A-2.A-1.#c.e.a.#c1.e1.a1)[M],(A-2.A-1.#c.e.a.#c1.e1.a1)[M],(A-2.A-1.#c.e.a.#c1.e1.a1)[M],(A-2.A-1.#c.e.a.#c1.e1.a1)[M],(A-2.A-1.#c.e.a.#c1.e1.a1)[M],(A-2.A-1.#c.e.a.#c1.e1.a1)[M],(A-2.A-1.#c.e.a.#c1.e1.a1)[M],(A-2.A-1.#c.e.a.#c1.e1.a1)[M],(A-2.A-1.#c.e.a.#c1.e1.a1)[M],(A-2.A-1.#c.e.a.#c1.e1.a1)[M],(A-2.A-1.#c.e.a.#c1.e1.a1)[M],(A-2.A-1.#c.e.a.#c1.e1.a1)[M],(A-2.A-1.#c.e.a.#c1.e1.a1)[M],(A-2.A-1.#c.e.a.#c1.e1.a1)[M],(A-2.A-1.#c.e.a.#c1.e1.a1)[M],(A-2.A-1.#c.e.a.#c1.e1.a1)[M],(A-2.A-1.#c.e.a.#c1.e1.a1)[M],(A-2.A-1.#c.e.a.#c1.e1.a1)[M],(A-2.A-1.#c.e.a.#c1.e1.a1)[M],(A-2.A-1.#c.e.a.#c1.e1.a1)[M],(A-2.A-1.#c.e.a.#c1.e1.a1)[M],(A-2.A-1.#c.e.a.#c1.e1.a1)[M],(A-2.A-1.#c.e.a.#c1.e1.a1)[M],(A-2.A-1.#c.e.a.#c1.e1.a1)[M],(A-2.A-1.#c.e.a.#c1.e1.a1)[M],(A-2.A-1.#c.e.a.#c1.e1.a1)[M],(A-2.A-1.#c.e.a.#c1.e1.a1)[M],(A-2.A-1.#c.e.a.#c1.e1.a1)[M],(A-2.A-1.#c.e.a.#c1.e1.a1)[M],(A-2.A-1.#c.e.a.#c1.e1.a1)[M],(A-2.A-1.#c.e.a.#c1.e1.a1)[M],(A-2.A-1.#c.e.a.#c1.e1.a1)[M],(A-2.A-1.#c.e.a.#c1.e1.a1)[M],(A-2.A-1.#c.e.a.#c1.e1.a1)[M],(A-2.A-1.#c.e.a.#c1.e1.a1)[M],(A-2.A-1.#c.e.a.#c1.e1.a1)[M],(A-2.A-1.#c.e.a.#c1.e1.a1)[M],(A-2.A-1.#c.e.a.#c1.e1.a1)[M],(A-2.A-1.#c.e.a.#c1.e1.a1)[M],(A-2.A-1.#c.e.a.#c1.e1.a1)[M],(A-2.A-1.#c.e.a.#c1.e1.a1)[M],(A-2.A-1.#c.e.a.#c1.e1.a1)[M],(A-2.A-1.#c.e.a.#c1.e1.a1)[M],(A-2.A-1.#c.e.a.#c1.e1.a1)[M],(A-2.A-1.#c.e.a.#c1.e1.a1)[M],(A-2.A-1.#c.e.a.#c1.e1.a1)[M],(A-2.A-1.#c.e.a.#c1.e1.a1)[M],(A-2.A-1.#c.e.a.#c1.e1.a1)[M],(A-2.A-1.#c.e.a.#c1.e1.a1)[M],(A-2.A-1.#c.e.a.#c1.e1.a1)[M],(A-2.A-1.#c.e.a.#c1.e1.a1)[M],(A-2.A-1.#c.e.a.#c1.e1.a1)[M],(A-2.A-1.#c.e.a.#c1.e1.a1)[M],(A-2.A-1.#c.e.a.#c1.e1.a1)[M],(A-2.A-1.#c.e.a.#c1.e1.a1)[M],(A-2.A-1.#c.e.a.#c1.e1.a1)[M],(A-2.A-1.#c.e.a.#c1.e1.a1)[M],(A-2.A-1.#c.e.a.#c1.e1.a1)[M],(A-2.A-1.#c.e.a.#c1.e1.a1)[M],(A-2.A-1.#c.e.a.#c1.e1.a1)[M],(A-2.A-1.#c.e.a.#c1.e1.a1)[M],(A-2.A-1.#c.e.a.#c1.e1.a1)[M],(A-2.A-1.#c.e.a.#c1.e1.a1)[M],(A-2.A-1.#c.e.a.#c1.e1.a1)[M],(A-2.A-1.#c.e.a.#c1.e1.a1)[M],(A-2.A-1.#c.e.a.#c1.e1.a1)[M],(A-2.A-1.#c.e.a.#c1.e1.a1)[M],(A-2.A-1.#c.e.a.#c1.e1.a1)[M],(A-2.A-1.#c.e.a.#c1.e1.a1)[M],(A-2.A-1.#c.e.a.#c1.e1.a1)[M],(A-2.A-1.#c.e.a.#c1.e1.a1)[M],(A-2.A-1.#c.e.a.#c1.e1.a1)[M],(A-2.A-1.#c.e.a.#c1.e1.a1)[M],(A-2.A-1.#c.e.a.#c1.e1.a1)[M],(A-2.A-1.#c.e.a.#c1.e1.a1)[M],(A-2.A-1.#c.e.a.#c1.e1.a1)[M],(A-2.A-1.#c.e.a.#c1.e1.a1)[M],(A-2.A-1.#c.e.a.#c1.e1.a1)[M],(A-2.A-1.#c.e.a.#c1.e1.a1)[M],(A-2.A-1.#c.e.a.#c1.e1.a1)[M],(A-2.A-1.#c.e.a.#c1.e1.a1)[M],(A-2.A-1.#c.e.a.#c1.e1.a1)[M],(A-2.A-1.#c.e.a.#c1.e1.a1)[M],(A-2.A-1.#c.e.a.#c1.e1.a1)[M],(A-2.A-1.#c.e.a.#c1.e1.a1)[M],(A-2.A-1.#c.e.a.#c1.e1.a1)[M],(A-2.A-1.#c.e.a.#c1.e1.a1)[M],(A-2.A-1.#c.e.a.#c1.e1.a1)[M],(A-2.A-1.#c.e.a.#c1.e1.a1)[M],(A-2.A-1.#c.e.a.#c1.e1.a1)[M],(A-2.A-1.#c.e.a.#c1.e1.a1)[M],(A-2.A-1.#c.e.a.#c1.e1.a1)[M],(A-2.A-1.#c.e.a.#c1.e1.a1)[M],(A-2.A-1.#c.e.a.#c1.e1.a1)[M],(A-2.A-1.#c.e.a.#c1.e1.a1)[M],(A-2.A-1.#c.e.a.#c1.e1.a1)[M],(A-2.A-1.#c.e.a.#c1.e1.a1)[M],(A-2.A-1.#c.e.a.#c1.e1.a1)[M],(A-2.A-1.#c.e.a.#c1.e1.a1)[M],(A-2.A-1.#c.e.a.#c1.e1.a1)[M],(A-2.A-1.#c.e.a.#c1.e1.a1)[M],(A-2.A-1.#c.e.a.#c1.e1.a1)[M],(A-2.A-1.#c.e.a.#c1.e1.a1)[M],(A-2.A-1.#c.e.a.#c1.e1.a1)[M],(A-2.A-1.#c.e.a.#c1.e1.a1)[M],(A-2.A-1.#c.e.a.#c1.e1.a1)[M],(A-2.A-1.#c.e.a.#c1.e1.a1)[M],(A-2.A-1.#c.e.a.#c1.e1.a1)[M],(A-2.A-1.#c.e.a.#c1.e1.a1)[M],(A-2.A-1.#c.e.a.#c1.e1.a1)[M],(A-2.A-1.#c.e.a.#c1.e1.a1)[M],(A-2.A-1.#c.e.a.#c1.e1.a1)[M],(A-2.A-1.#c.e.a.#c1.e1.a1)[M],(A-2.A-1.#c.e.a.#c1.e1.a1)[M],(A-2.A-1.#c.e.a.#c1.e1.a1)[M],(A-2.A-1.#c.e.a.#c1.e1.a1)[M],(A-2.A-1.#c.e.a.#c1.e1.a1)[M],(A-2.A-1.#c.e.a.#c1.e1.a1)[M],(A-2.A-1.#c.e.a.#c1.e1.a1)[M],(A-2.A-1.#c.e.a.#c1.e1.a1)[M],(A-2.A-1.#c.e.a.#c1.e1.a1)[M],(A-2.A-1.#c.e.a.#c1.e1.a1)[M],(A-2.A-1.#c.e.a.#c1.e1.a1)[M],(A-2.A-1.#c.e.a.#c1.e1.a1)[M],(A-2.A-1.#c.e.a.#c1.e1.a1)[M],(A-2.A-1.#c.e.a.#c1.e1.a1)[M],(A-2.A-1.#c.e.a.#c1.e1.a1)[M],(A-2.A-1.#c.e.a.#c1.e1.a1)[M],(A-2.A-1.#c.e.a.#c1.e1.a1)[M],(A-2.A-1.#c.e.a.#c1.e1.a1)[M],(A-2.A-1.#c.e.a.#c1.e1.a1)[M],(A-2.A-1.#c.e.a.#c1.e1.a1)[M],(A-2.A-1.#c.e.a.#c1.e1.a1)[M],(A-2.A-1.#c.e.a.#c1.e1.a1)[M],(A-2.A-1.#c.e.a.#c1.e1.a1)[M],(A-2.A-1.#c.e.a.#c1.e1.a1)[M],(A-2.A-1.#c.e.a.#c1.e1.a1)[M],(A-2.A-1.#c.e.a.#c1.e1.a1)[M],(A-2.A-1.#c.e.a.#c1.e1.a1)[M],(A-2.A-1.#c.e.a.#c1.e1.a1)[M],(A-2.A-1.#c.e.a.#c1.e1.a1)[M],(A-2.A-1.#c.e.a.#c1.e1.a1)[M],(A-2.A-1.#c.e.a.#c1.e1.a1)[M],(A-2.A-1.#c.e.a.#c1.e1.a1)[M],(A-2.A-1.#c.e.a.#c1.e1.a1)[M],(A-2.A-1.#c.e.a.#c1.e1.a1)[M],(A-2.A-1.#c.e.a.#c1.e1.a1)[M],(A-2.A-1.#c.e.a.#c1.e1.a1)[M],(A-2.A-1.#c.e.a.#c1.e1.a1)[M],(A-2.A-1.#c.e.a.#c1.e1.a1)[M],(A-2.A-1.#c.e.a.#c1.e1.a1)[M],(A-2.A-1.#c.e.a.#c1.e1.a1)[M],(A-2.A-1.#c.e.a.#c1.e1.a1)[M],(A-2.A-1.#c.e.a.#c1.e1.a1)[M],(A-2.A-1.#c.e.a.#c1.e1.a1)[M],(A-2.A-1.#c.e.a.#c1.e1.a1)[M],(A-2.A-1.#c.e.a.#c1.e1.a1)[M],(A-2.A-1.#c.e.a.#c1.e1.a1)[M],(A-2.A-1.#c.e.a.#c1.e1.a1)[M],(A-2.A-1.#c.e.a.#c1.e1.a1)[M],(A-2.A-1.#c.e.a.#c1.e1.a1)[M],(A-2.A-1.#c.e.a.#c1.e1.a1)[M],(A-2.A-1.#c.e.a.#c1.e1.a1)[M],(A-2.A-1.#c.e.a.#c1.e1.a1)[M],(A-2.A-1.#c.e.a.#c1.e1.a1)[M],(A-2.A-1.#c.e.a.#c1.e1.a1)[M],(A-2.A-1.#c.e.a.#c1.e1.a1)[M],(A-2.A-1.#c.e.a.#c1.e1.a1)[M],(A-2.A-1.#c.e.a.#c1.e1.a1)[M],(A-2.A-1.#c.e.a.#c1.e1.a1)[M],(A-2.A-1.#c.e.a.#c1.e1.a1)[M],(A-2.A-1.#c.e.a.#c1.e1.a1)[M],(A-2.A-1.#c.e.a.#c1.e1.a1)[M],(A-2.A-1.#c.e.a.#c1.e1.a1)[M],(A-2.A-1.#c.e.a.#c1.e1.a1)[M],(A-2.A-1.#c.e.a.#c1.e1.a1)[M],(A-2.A-1.#c.e.a.#c1.e1.a1)[M],(A-2.A-1.#c.e.a.#c1.e1.a1)[M],(A-2.A-1.#c.e.a.#c1.e1.a1)[M],(A-2.A-1.#c.e.a.#c1.e1.a1)[M],(A-2.A-1.#c.e.a.#c1.e1.a1)[M],(A-2.A-1.#c.e.a.#c1.e1.a1)[M],(A-2.A-1.#c.e.a.#c1.e1.a1)[M],(A-2.A-1.#c.e.a.#c1.e1.a1)[M],(A-2.A-1.#c.e.a.#c1.e1.a1)[M],(A-2.A-1.#c.e.a.#c1.e1.a1)[M],(A-2.A-1.#c.e.a.#c1.e1.a1)[M],(A-2.A-1.#c.e.a.#c1.e1.a1)[M],(A-2.A-1.#c.e.a.#c1.e1.a1)[M],(A-2.A-1.#c.e.a.#c1.e1.a1)[M],(A-2.A-1.#c.e.a.#c1.e1.a1)[M],(A-2.A-1.#c.e.a.#c1.e1.a1)[M],(A-2.A-1.#c.e.a.#c1.e1.a1)[M],(A-2.A-1.#c.e.a.#c1.e1.a1)[M],(A-2.A-1.#c.e.a.#c1.e1.a1)[M],(A-2.A-1.#c.e.a.#c1.e1.a1)[M],(A-2.A-1.#c.e.a.#c1.e1.a1)[M],(A-2.A-1.#c.e.a.#c1.e1.a1)[M],(A-2.A-1.#c.e.a.#c1.e1.a1)[M],(A-2.A-1.#c.e.a.#c1.e1.a1)[M],(A-2.A-1.#c.e.a.#c1.e1.a1)[M],(A-2.A-1.#c.e.a.#c1.e1.a1)[M],(A-2.A-1.#c.e.a.#c1.e1.a1)[M],(A-2.A-1.#c.e.a.#c1.e1.a1)[M],(A-2.A-1.#c.e.a.#c1.e1.a1)[M],(A-2.A-1.#c.e.a.#c1.e1.a1)[M],(A-2.A-1.#c.e.a.#c1.e1.a1)[M],(A-2.A-1.#c.e.a.#c1.e1.a1)[M],(A-2.A-1.#c.e.a.#c1.e1.a1)[M],(A-2.A-1.#c.e.a.#c1.e1.a1)[M],(A-2.A-1.#c.e.a.#c1.e1.a1)[M],(A-2.A-1.#c.e.a.#c1.e1.a1)[M],(A-2.A-1.#c.e.a.#c1.e1.a1)[M],(A-2.A-1.#c.e.a.#c1.e1.a1)[M],(A-2.A-1.#c.e.a.#c1.e1.a1)[M],(A-2.A-1.#c.e.a.#c1.e1.a1)[M],(A-2.A-1.#c.e.a.#c1.e1.a1)[M],(A-2.A-1.#c.e.a.#c1.e1.a1)[M],(A-2.A-1.#c.e.a.#c1.e1.a1)[M],(A-2.A-1.#c.e.a.#c1.e1.a1)[M],(A-2.A-1.#c.e.a.#c1.e1.a1)[M],(A-2.A-1.#c.e.a.#c1.e1.a1)[M],(A-2.A-1.#c.e.a.#c1.e1.a1)[M],(A-2.A-1.#c.e.a.#c1.e1.a1)[M],(A-2.A-1.#c.e.a.#c1.e1.a1)[M],(A-2.A-1.#c.e.a.#c1.e1.a1)[M],(A-2.A-1.#c.e.a.#c1.e1.a1)[M],(A-2.A-1.#c.e.a.#c1.e1.a1)[M],(A-2.A-1.#c.e.a.#c1.e1.a1)[M],(A-2.A-1.#c.e.a.#c1.e1.a1)[M],(A-2.A-1.#c.e.a.#c1.e1.a1)[M],(A-2.A-1.#c.e.a.#c1.e1.a1)[M],(A-2.A-1.#c.e.a.#c1.e1.a1)[M],(A-2.A-1.#c.e.a.#c1.e1.a1)[M],(A-2.A-1.#c.e.a.#c1.e1.a1)[M],(A-2.A-1.#c.e.a.#c1.e1.a1)[M],(A-2.A-1.#c.e.a.#c1.e1.a1)[M],(A-2.A-1.#c.e.a.#c1.e1.a1)[M],(A-2.A-1.#c.e.a.#c1.e1.a1)[M],(A-2.A-1.#c.e.a.#c1.e1.a1)[M],(A-2.A-1.#c.e.a.#c1.e1.a1)[M],(A-2.A-1.#c.e.a.#c1.e1.a1)[M],(A-2.A-1.#c.e.a.#c1.e1.a1)[M],(A-2.A-1.#c.e.a.#c1.e1.a1)[M],(A-2.A-1.#c.e.a.#c1.e1.a1)[M],(A-2.A-1.#c.e.a.#c1.e1.a1)[M],(A-2.A-1.#c.e.a.#c1.e1.a1)[M],(A-2.A-1.#c.e.a.#c1.e1.a1)[M],(A-2.A-1.#c.e.a.#c1.e1.a1)[M],(A-2.A-1.#c.e.a.#c1.e1.a1)[M],(A-2.A-1.#c.e.a.#c1.e1.a1)[M],(A-2.A-1.#c.e.a.#c1.e1.a1)[M],(A-2.A-1.#c.e.a.#c1.e1.a1)[M],(A-2.A-1.#c.e.a.#c1.e1.a1)[M],(A-2.A-1.#c.e.a.#c1.e1.a1)[M],(A-2.A-1.#c.e.a.#c1.e1.a1)[M],(A-2.A-1.#c.e.a.#c1.e1.a1)[M],(A-2.A-1.#c.e.a.#c1.e1.a1)[M],(A-2.A-1.#c.e.a.#c1.e1.a1)[M],(A-2.A-1.#c.e.a.#c1.e1.a1)[M],(A-2.A-1.#c.e.a.#c1.e1.a1)[M],(A-2.A-1.#c.e.a.#c1.e1.a1)[M],(A-2.A-1.#c.e.a.#c1.e1.a1)[M],(A-2.A-1.#c.e.a.#c1.e1.a1)[M],(A-2.A-1.#c.e.a.#c1.e1.a1)[M],(A-2.A-1.#c.e.a.#c1.e1.a1)[M],(A-2.A-1.#c.e.a.#c1.e1.a1)[M],(A-2.A-1.#c.e.a.#c1.e1.a1)[M],(A-2.A-1.#c.e.a.#c1.e1.a1)[M],(A-2.A-1.#c.e.a.#c1.e1.a1)[M],(A-2.A-1.#c.e.a.#c1.e1.a1)[M],(A-2.A-1.#c.e.a.#c1.e1.a1)[M],(A-2.A-1.#c.e.a.#c1.e1.a1)[M],(A-2.A-1.#c.e.a.#c1.e1.a1)[M],(A-2.A-1.#c.e.a.#c1.e1.a1)[M],(A-2.A-1.#c.e.a.#c1.e1.a1)[M],(A-2.A-1.#c.e.a.#c1.e1.a1)[M],(A-2.A-1.#c.e.a.#c1.e1.a1)[M],(A-2.A-1.#c.e.a.#c1.e1.a1)[M],(A-2.A-1.#c.e.a.#c1.e1.a1)[M],(A-2.A-1.#c.e.a.#c1.e1.a1)[M],(A-2.A-1.#c.e.a.#c1.e1.a1)[M],(A-2.A-1.#c.e.a.#c1.e1.a1)[M],(A-2.A-1.#c.e.a.#c1.e1.a1)[M],(A-2.A-1.#c.e.a.#c1.e1.a1)[M],(A-2.A-1.#c.e.a.#c1.e1.a1)[M],(A-2.A-1.#c.e.a.#c1.e1.a1)[M],(A-2.A-1.#c.e.a.#c1.e1.a1)[M],(A-2.A-1.#c.e.a.#c1.e1.a1)[M],(A-2.A-1.#c.e.a.#c1.e1.a1)[M],(A-2.A-1.#c.e.a.#c1.e1.a1)[M],(A-2.A-1.#c.e.a.#c1.e1.a1)[M],(A-2.A-1.#c.e.a.#c1.e1.a1)[M],(A-2.A-1.#c.e.a.#c1.e1.a1)[M],(A-2.A-1.#c.e.a.#c1.e1.a1)[M],(A-2.A-1.#c.e.a.#c1.e1.a1)[M],(A-2.A-1.#c.e.a.#c1.e1.a1)[M],(A-2.A-1.#c.e.a.#c1.e1.a1)[M],(A-2.A-1.#c.e.a.#c1.e1.a1)[M],(A-2.A-1.#c.e.a.#c1.e1.a1)[M],(A-2.A-1.#c.e.a.#c1.e1.a1)[M],(A-2.A-1.#c.e.a.#c1.e1.a1)[M],(A-2.A-1.#c.e.a.#c1.e1.a1)[M],(A-2.A-1.#c.e.a.#c1.e1.a1)[M],(A-2.A-1.#c.e.a.#c1.e1.a1)[M],(A-2.A-1.#c.e.a.#c1.e1.a1)[M],(A-2.A-1.#c.e.a.#c1.e1.a1)[M],(A-2.A-1.#c.e.a.#c1.e1.a1)[M],(A-2.A-1.#c.e.a.#c1.e1.a1)[M],(A-2.A-1.#c.e.a.#c1.e1.a1)[M],(A-2.A-1.#c.e.a.#c1.e1.a1)[M],(A-2.A-1.#c.e.a.#c1.e1.a1)[M],(A-2.A-1.#c.e.a.#c1.e1.a1)[M],(A-2.A-1.#c.e.a.#c1.e1.a1)[M],(A-2.A-1.#c.e.a.#c1.e1.a1)[M],(A-2.A-1.#c.e.a.#c1.e1.a1)[M],(A-2.A-1.#c.e.a.#c1.e1.a1)[M],(A-2.A-1.#c.e.a.#c1.e1.a1)[M],(A-2.A-1.#c.e.a.#c1.e1.a1)[M],(A-2.A-1.#c.e.a.#c1.e1.a1)[M],(A-2.A-1.#c.e.a.#c1.e1.a1)[M],(A-2.A-1.#c.e.a.#c1.e1.a1)[M],(A-2.A-1.#c.e.a.#c1.e1.a1)[M],(A-2.A-1.#c.e.a.#c1.e1.a1)[M],(A-2.A-1.#c.e.a.#c1.e1.a1)[M],(A-2.A-1.#c.e.a.#c1.e1.a1)[M],(A-2.A-1.#c.e.a.#c1.e1.a1)[M],(A-2.A-1.#c.e.a.#c1.e1.a1)[M],(A-2.A-1.#c.e.a.#c1.e1.a1)[M],(A-2.A-1.#c.e.a.#c1.e1.a1)[M],(A-2.A-1.#c.e.a.#c1.e1.a1)[M],(A-2.A-1.#c.e.a.#c1.e1.a1)[M],(A-2.A-1.#c.e.a.#c1.e1.a1)[M],(A-2.A-1.#c.e.a.#c1.e1.a1)[M],(A-2.A-1.#c.e.a.#c1.e1.a1)[M],(A-2.A-1.#c.e.a.#c1.e1.a1)[M],(A-2.A-1.#c.e.a.#c1.e1.a1)[M],(A-2.A-1.#c.e.a.#c1.e1.a1)[M],(A-2.A-1.#c.e.a.#c1.e1.a1)[M],(A-2.A-1.#c.e.a.#c1.e1.a1)[M],(A-2.A-1.#c.e.a.#c1.e1.a1)[M],(A-2.A-1.#c.e.a.#c1.e1.a1)[M],(A-2.A-1.#c.e.a.#c1.e1.a1)[M],(A-2.A-1.#c.e.a.#c1.e1.a1)[M],(A-2.A-1.#c.e.a.#c1.e1.a1)[M],(A-2.A-1.#c.e.a.#c1.e1.a1)[M],(A-2.A-1.#c.e.a.#c1.e1.a1)[M],(A-2.A-1.#c.e.a.#c1.e1.a1)[M],(A-2.A-1.#c.e.a.#c1.e1.a1)[M],(A-2.A-1.#c.e.a.#c1.e1.a1)[M],(A-2.A-1.#c.e.a.#c1.e1.a1)[M],(A-2.A-1.#c.e.a.#c1.e1.a1)[M],(A-2.A-1.#c.e.a.#c1.e1.a1)[M],(A-2.A-1.#c.e.a.#c1.e1.a1)[M],(A-2.A-1.#c.e.a.#c1.e1.a1)[M],(A-2.A-1.#c.e.a.#c1.e1.a1)[M],(A-2.A-1.#c.e.a.#c1.e1.a1)[M],(A-2.A-1.#c.e.a.#c1.e1.a1)[M],(A-2.A-1.#c.e.a.#c1.e1.a1)[M],(A-2.A-1.#c.e.a.#c1.e1.a1)[M],(A-2.A-1.#c.e.a.#c1.e1.a1)[M],(A-2.A-1.#c.e.a.#c1.e1.a1)[M],(A-2.A-1.#c.e.a.#c1.e1.a1)[M],(A-2.A-1.#c.e.a.#c1.e1.a1)[M],(A-2.A-1.#c.e.a.#c1.e1.a1)[M],(A-2.A-1.#c.e.a.#c1.e1.a1)[M],(A-2.A-1.#c.e.a.#c1.e1.a1)[M],(A-2.A-1.#c.e.a.#c1.e1.a1)[M],(A-2.A-1.#c.e.a.#c1.e1.a1)[M],(A-2.A-1.#c.e.a.#c1.e1.a1)[M],(A-2.A-1.#c.e.a.#c1.e1.a1)[M],(A-2.A-1.#c.e.a.#c1.e1.a1)[M],(A-2.A-1.#c.e.a.#c1.e1.a1)[M],(A-2.A-1.#c.e.a.#c1.e1.a1)[M],(A-2.A-1.#c.e.a.#c1.e1.a1)[M],(A-2.A-1.#c.e.a.#c1.e1.a1)[M],(A-2.A-1.#c.e.a.#c1.e1.a1)[M],(A-2.A-1.#c.e.a.#c1.e1.a1)[M],(A-2.A-1.#c.e.a.#c1.e1.a1)[M],(A-2.A-1.#c.e.a.#c1.e1.a1)[M],(A-2.A-1.#c.e.a.#c1.e1.a1)[M],(A-2.A-1.#c.e.a.#c1.e1.a1)[M],(A-2.A-1.#c.e.a.#c1.e1.a1)[M],(A-2.A-1.#c.e.a.#c1.e1.a1)[M],(A-2.A-1.#c.e.a.#c1.e1.a1)[M],(A-2.A-1.#c.e.a.#c1.e1.a1)[M],(A-2.A-1.#c.e.a.#c1.e1.a1)[M],(A-2.A-1.#c.e.a.#c1.e1.a1)[M],(A-2.A-1.#c.e.a.#c1.e1.a1)[M],(A-2.A-1.#c.e.a.#c1.e1.a1)[M],(A-2.A-1.#c.e.a.#c1.e1.a1)[M],(A-2.A-1.#c.e.a.#c1.e1.a1)[M],(A-2.A-1.#c.e.a.#c1.e1.a1)[M],(A-2.A-1.#c.e.a.#c1.e1.a1)[M],(A-2.A-1.#c.e.a.#c1.e1.a1)[M],(A-2.A-1.#c.e.a.#c1.e1.a1)[M],(A-2.A-1.#c.e.a.#c1.e1.a1)[M],(A-2.A-1.#c.e.a.#c1.e1.a1)[M],(A-2.A-1.#c.e.a.#c1.e1.a1)[M],(A-2.A-1.#c.e.a.#c1.e1.a1)[M],(A-2.A-1.#c.e.a.#c1.e1.a1)[M],(A-2.A-1.#c.e.a.#c1.e1.a1)[M],(A-2.A-1.#c.e.a.#c1.e1.a1)[M],(A-2.A-1.#c.e.a.#c1.e1.a1)[M],(A-2.A-1.#c.e.a.#c1.e1.a1)[M],(A-2.A-1.#c.e.a.#c1.e1.a1)[M],(A-2.A-1.#c.e.a.#c1.e1.a1)[M],(A-2.A-1.#c.e.a.#c1.e1.a1)[M],(A-2.A-1.#c.e.a.#c1.e1.a1)[M],(A-2.A-1.#c.e.a.#c1.e1.a1)[M],(A-2.A-1.#c.e.a.#c1.e1.a1)[M],(A-2.A-1.#c.e.a.#c1.e1.a1)[M],(A-2.A-1.#c.e.a.#c1.e1.a1)[M],(A-2.A-1.#c.e.a.#c1.e1.a1)[M],(A-2.A-1.#c.e.a.#c1.e1.a1)[M],(A-2.A-1.#c.e.a.#c1.e1.a1)[M],(A-2.A-1.#c.e.a.#c1.e1.a1)[M],(A-2.A-1.#c.e.a.#c1.e1.a1)[M],(A-2.A-1.#c.e.a.#c1.e1.a1)[M],(A-2.A-1.#c.e.a.#c1.e1.a1)[M],(A-2.A-1.#c.e.a.#c1.e1.a1)[M],(A-2.A-1.#c.e.a.#c1.e1.a1)[M],(A-2.A-1.#c.e.a.#c1.e1.a1)[M],(A-2.A-1.#c.e.a.#c1.e1.a1)[M],(A-2.A-1.#c.e.a.#c1.e1.a1)[M],(A-2.A-1.#c.e.a.#c1.e1.a1)[M],(A-2.A-1.#c.e.a.#c1.e1.a1)[M],(A-2.A-1.#c.e.a.#c1.e1.a1)[M],(A-2.A-1.#c.e.a.#c1.e1.a1)[M],(A-2.A-1.#c.e.a.#c1.e1.a1)[M],(A-2.A-1.#c.e.a.#c1.e1.a1)[M],(A-2.A-1.#c.e.a.#c1.e1.a1)[M],(A-2.A-1.#c.e.a.#c1.e1.a1)[M],(A-2.A-1.#c.e.a.#c1.e1.a1)[M],(A-2.A-1.#c.e.a.#c1.e1.a1)[M],(A-2.A-1.#c.e.a.#c1.e1.a1)[M],(A-2.A-1.#c.e.a.#c1.e1.a1)[M],(A-2.A-1.#c.e.a.#c1.e1.a1)[M],(A-2.A-1.#c.e.a.#c1.e1.a1)[M],(A-2.A-1.#c.e.a.#c1.e1.a1)[M],(A-2.A-1.#c.e.a.#c1.e1.a1)[M],(A-2.A-1.#c.e.a.#c1.e1.a1)[M],(A-2.A-1.#c.e.a.#c1.e1.a1)[M],(A-2.A-1.#c.e.a.#c1.e1.a1)[M],(A-2.A-1.#c.e.a.#c1.e1.a1)[M],(A-2.A-1.#c.e.a.#c1.e1.a1)[M],(A-2.A-1.#c.e.a.#c1.e1.a1)[M],(A-2.A-1.#c.e.a.#c1.e1.a1)[M],(A-2.A-1.#c.e.a.#c1.e1.a1)[M],(A-2.A-1.#c.e.a.#c1.e1.a1)[M],(A-2.A-1.#c.e.a.#c1.e1.a1)[M],(A-2.A-1.#c.e.a.#c1.e1.a1)[M],(A-2.A-1.#c.e.a.#c1.e1.a1)[M],(A-2.A-1.#c.e.a.#c1.e1.a1)[M],(A-2.A-1.#c.e.a.#c1.e1.a1)[M],(A-2.A-1.#c.e.a.#c1.e1.a1)[M],(A-2.A-1.#c.e.a.#c1.e1.a1)[M],(A-2.A-1.#c.e.a.#c1.e1.a1)[M],(A-2.A-1.#c.e.a.#c1.e1.a1)[M],(A-2.A-1.#c.e.a.#c1.e1.a1)[M],(A-2.A-1.#c.e.a.#c1.e1.a1)[M],(A-2.A-1.#c.e.a.#c1.e1.a1)[M],(A-2.A-1.#c.e.a.#c1.e1.a1)[M],(A-2.A-1.#c.e.a.#c1.e1.a1)[M],(A-2.A-1.#c.e.a.#c1.e1.a1)[M],(A-2.A-1.#c.e.a.#c1.e1.a1)[M],(A-2.A-1.#c.e.a.#c1.e1.a1)[M],(A-2.A-1.#c.e.a.#c1.e1.a1)[M],(A-2.A-1.#c.e.a.#c1.e1.a1)[M],(A-2.A-1.#c.e.a.#c1.e1.a1)[M],(A-2.A-1.#c.e.a.#c1.e1.a1)[M],(A-2.A-1.#c.e.a.#c1.e1.a1)[M],(A-2.A-1.#c.e.a.#c1.e1.a1)[M],(A-2.A-1.#c.e.a.#c1.e1.a1)[M],(A-2.A-1.#c.e.a.#c1.e1.a1)[M],(A-2.A-1.#c.e.a.#c1.e1.a1)[M],(A-2.A-1.#c.e.a.#c1.e1.a1)[M],(A-2.A-1.#c.e.a.#c1.e1.a1)[M],(A-2.A-1.#c.e.a.#c1.e1.a1)[M],(A-2.A-1.#c.e.a.#c1.e1.a1)[M],(A-2.A-1.#c.e.a.#c1.e1.a1)[M],(A-2.A-1.#c.e.a.#c1.e1.a1)[M],(A-2.A-1.#c.e.a.#c1.e1.a1)[M],(A-2.A-1.#c.e.a.#c1.e1.a1)[M],(A-2.A-1.#c.e.a.#c1.e1.a1)[M],(A-2.A-1.#c.e.a.#c1.e1.a1)[M],(A-2.A-1.#c.e.a.#c1.e1.a1)[M],(A-2.A-1.#c.e.a.#c1.e1.a1)[M],(A-2.A-1.#c.e.a.#c1.e1.a1)[M],(A-2.A-1.#c.e.a.#c1.e1.a1)[M],(A-2.A-1.#c.e.a.#c1.e1.a1)[M],(A-2.A-1.#c.e.a.#c1.e1.a1)[M],(A-2.A-1.#c.e.a.#c1.e1.a1)[M],(A-2.A-1.#c.e.a.#c1.e1.a1)[M],(A-2.A-1.#c.e.a.#c1.e1.a1)[M],(A-2.A-1.#c.e.a.#c1.e1.a1)[M],(A-2.A-1.#c.e.a.#c1.e1.a1)[M],(A-2.A-1.#c.e.a.#c1.e1.a1)[M],(A-2.A-1.#c.e.a.#c1.e1.a1)[M],(A-2.A-1.#c.e.a.#c1.e1.a1)[M],(A-2.A-1.#c.e.a.#c1.e1.a1)[M],(A-2.A-1.#c.e.a.#c1.e1.a1)[M],(A-2.A-1.#c.e.a.#c1.e1.a1)[M],(A-2.A-1.#c.e.a.#c1.e1.a1)[M],(A-2.A-1.#c.e.a.#c1.e1.a1)[M],(A-2.A-1.#c.e.a.#c1.e1.a1)[M],(A-2.A-1.#c.e.a.#c1.e1.a1)[M],(A-2.A-1.#c.e.a.#c1.e1.a1)[M],(A-2.A-1.#c.e.a.#c1.e1.a1)[M],(A-2.A-1.#c.e.a.#c1.e1.a1)[M],(A-2.A-1.#c.e.a.#c1.e1.a1)[M],(A-2.A-1.#c.e.a.#c1.e1.a1)[M],(A-2.A-1.#c.e.a.#c1.e1.a1)[M],(A-2.A-1.#c.e.a.#c1.e1.a1)[M],(A-2.A-1.#c.e.a.#c1.e1.a1)[M],(A-2.A-1.#c.e.a.#c1.e1.a1)[M],(A-2.A-1.#c.e.a.#c1.e1.a1)[M],(A-2.A-1.#c.e.a.#c1.e1.a1)[M],(A-2.A-1.#c.e.a.#c1.e1.a1)[M],(A-2.A-1.#c.e.a.#c1.e1.a1)[M],(A-2.A-1.#c.e.a.#c1.e1.a1)[M],(A-2.A-1.#c.e.a.#c1.e1.a1)[M],(A-2.A-1.#c.e.a.#c1.e1.a1)[M],(A-2.A-1.#c.e.a.#c1.e1.a1)[M],(A-2.A-1.#c.e.a.#c1.e1.a1)[M],(A-2.A-1.#c.e.a.#c1.e1.a1)[M],(A-2.A-1.#c.e.a.#c1.e1.a1)[M],(A-2.A-1.#c.e.a.#c1.e1.a1)[M],(A-2.A-1.#c.e.a.#c1.e1.a1)[M],(A-2.A-1.#c.e.a.#c1.e1.a1)[M],(A-2.A-1.#c.e.a.#c1.e1.a1)[M],(A-2.A-1.#c.e.a.#c1.e1.a1)[M],(A-2.A-1.#c.e.a.#c1.e1.a1)[M],(A-2.A-1.#c.e.a.#c1.e1.a1)[M],(A-2.A-1.#c.e.a.#c1.e1.a1)[M],(A-2.A-1.#c.e.a.#c1.e1.a1)[M],(A-2.A-1.#c.e.a.#c1.e1.a1)[M],(A-2.A-1.#c.e.a.#c1.e1.a1)[M],(A-2.A-1.#c.e.a.#c1.e1.a1)[M],(A-2.A-1.#c.e.a.#c1.e1.a1)[M],(A-2.A-1.#c.e.a.#c1.e1.a1)[M],(A-2.A-1.#c.e.a.#c1.e1.a1)[M],(A-2.A-1.#c.e.a.#c1.e1.a1)[M],(A-2.A-1.#c.e.a.#c1.e1.a1)[M],(A-2.A-1.#c.e.a.#c1.e1.a1)[M],(A-2.A-1.#c.e.a.#c1.e1.a1)[M],(A-2.A-1.#c.e.a.#c1.e1.a1)[M],(A-2.A-1.#c.e.a.#c1.e1.a1)[M],(A-2.A-1.#c.e.a.#c1.e1.a1)[M],(A-2.A-1.#c.e.a.#c1.e1.a1)[M],(A-2.A-1.#c.e.a.#c1.e1.a1)[M],(A-2.A-1.#c.e.a.#c1.e1.a1)[M],(A-2.A-1.#c.e.a.#c1.e1.a1)[M],(A-2.A-1.#c.e.a.#c1.e1.a1)[M],(A-2.A-1.#c.e.a.#c1.e1.a1)[M],(A-2.A-1.#c.e.a.#c1.e1.a1)[M],(A-2.A-1.#c.e.a.#c1.e1.a1)[M],(A-2.A-1.#c.e.a.#c1.e1.a1)[M],(A-2.A-1.#c.e.a.#c1.e1.a1)[M],(A-2.A-1.#c.e.a.#c1.e1.a1)[M],(A-2.A-1.#c.e.a.#c1.e1.a1)[M],(A-2.A-1.#c.e.a.#c1.e1.a1)[M],(A-2.A-1.#c.e.a.#c1.e1.a1)[M],(A-2.A-1.#c.e.a.#c1.e1.a1)[M],(A-2.A-1.#c.e.a.#c1.e1.a1)[M],(A-2.A-1.#c.e.a.#c1.e1.a1)[M],(A-2.A-1.#c.e.a.#c1.e1.a1)[M],(A-2.A-1.#c.e.a.#c1.e1.a1)[M],(A-2.A-1.#c.e.a.#c1.e1.a1)[M],(A-2.A-1.#c.e.a.#c1.e1.a1)[M],(A-2.A-1.#c.e.a.#c1.e1.a1)[M],(A-2.A-1.#c.e.a.#c1.e1.a1)[M],(A-2.A-1.#c.e.a.#c1.e1.a1)[M],(A-2.A-1.#c.e.a.#c1.e1.a1)[M],(A-2.A-1.#c.e.a.#c1.e1.a1)[M],(A-2.A-1.#c.e.a.#c1.e1.a1)[M],(A-2.A-1.#c.e.a.#c1.e1.a1)[M],(A-2.A-1.#c.e.a.#c1.e1.a1)[M],(A-2.A-1.#c.e.a.#c1.e1.a1)[M],(A-2.A-1.#c.e.a.#c1.e1.a1)[M],(A-2.A-1.#c.e.a.#c1.e1.a1)[M],(A-2.A-1.#c.e.a.#c1.e1.a1)[M],(A-2.A-1.#c.e.a.#c1.e1.a1)[M],(A-2.A-1.#c.e.a.#c1.e1.a1)[M],(A-2.A-1.#c.e.a.#c1.e1.a1)[M],(A-2.A-1.#c.e.a.#c1.e1.a1)[M],(A-2.A-1.#c.e.a.#c1.e1.a1)[M],(A-2.A-1.#c.e.a.#c1.e1.a1)[M],(A-2.A-1.#c.e.a.#c1.e1.a1)[M],(A-2.A-1.#c.e.a.#c1.e1.a1)[M],(A-2.A-1.#c.e.a.#c1.e1.a1)[M],(A-2.A-1.#c.e.a.#c1.e1.a1)[M],(A-2.A-1.#c.e.a.#c1.e1.a1)[M],(A-2.A-1.#c.e.a.#c1.e1.a1)[M],(A-2.A-1.#c.e.a.#c1.e1.a1)[M],(A-2.A-1.#c.e.a.#c1.e1.a1)[M],(A-2.A-1.#c.e.a.#c1.e1.a1)[M],(A-2.A-1.#c.e.a.#c1.e1.a1)[M],(A-2.A-1.#c.e.a.#c1.e1.a1)[M],(A-2.A-1.#c.e.a.#c1.e1.a1)[M],(A-2.A-1.#c.e.a.#c1.e1.a1)[M],(A-2.A-1.#c.e.a.#c1.e1.a1)[M],(A-2.A-1.#c.e.a.#c1.e1.a1)[M],(A-2.A-1.#c.e.a.#c1.e1.a1)[M],(A-2.A-1.#c.e.a.#c1.e1.a1)[M],(A-2.A-1.#c.e.a.#c1.e1.a1)[M],(A-2.A-1.#c.e.a.#c1.e1.a1)[M],(A-2.A-1.#c.e.a.#c1.e1.a1)[M],(A-2.A-1.#c.e.a.#c1.e1.a1)[M],(A-2.A-1.#c.e.a.#c1.e1.a1)[M],(A-2.A-1.#c.e.a.#c1.e1.a1)[M],(A-2.A-1.#c.e.a.#c1.e1.a1)[M],(A-2.A-1.#c.e.a.#c1.e1.a1)[M],(A-2.A-1.#c.e.a.#c1.e1.a1)[M],(A-2.A-1.#c.e.a.#c1.e1.a1)[M],(A-2.A-1.#c.e.a.#c1.e1.a1)[M],(A-2.A-1.#c.e.a.#c1.e1.a1)[M],(A-2.A-1.#c.e.a.#c1.e1.a1)[M],(A-2.A-1.#c.e.a.#c1.e1.a1)[M],(A-2.A-1.#c.e.a.#c1.e1.a1)[M],(A-2.A-1.#c.e.a.#c1.e1.a1)[M],(A-2.A-1.#c.e.a.#c1.e1.a1)[M],(A-2.A-1.#c.e.a.#c1.e1.a1)[M],(A-2.A-1.#c.e.a.#c1.e1.a1)[M],(A-2.A-1.#c.e.a.#c1.e1.a1)[M],(A-2.A-1.#c.e.a.#c1.e1.a1)[M],(A-2.A-1.#c.e.a.#c1.e1.a1)[M],(A-2.A-1.#c.e.a.#c1.e1.a1)[M],(A-2.A-1.#c.e.a.#c1.e1.a1)[M],(A-2.A-1.#c.e.a.#c1.e1.a1)[M],(A-2.A-1.#c.e.a.#c1.e1.a1)[M],(A-2.A-1.#c.e.a.#c1.e1.a1)[M],(A-2.A-1.#c.e.a.#c1.e1.a1)[M],(A-2.A-1.#c.e.a.#c1.e1.a1)[M],(A-2.A-1.#c.e.a.#c1.e1.a1)[M],(A-2.A-1.#c.e.a.#c1.e1.a1)[M],(A-2.A-1.#c.e.a.#c1.e1.a1)[M],(A-2.A-1.#c.e.a.#c1.e1.a1)[M],(A-2.A-1.#c.e.a.#c1.e1.a1)[M],(A-2.A-1.#c.e.a.#c1.e1.a1)[M],(A-2.A-1.#c.e.a.#c1.e1.a1)[M],(A-2.A-1.#c.e.a.#c1.e1.a1)[M],(A-2.A-1.#c.e.a.#c1.e1.a1)[M],(A-2.A-1.#c.e.a.#c1.e1.a1)[M],(A-2.A-1.#c.e.a.#c1.e1.a1)[M],(A-2.A-1.#c.e.a.#c1.e1.a1)[M],(A-2.A-1.#c.e.a.#c1.e1.a1)[M],(A-2.A-1.#c.e.a.#c1.e1.a1)[M],(A-2.A-1.#c.e.a.#c1.e1.a1)[M],(A-2.A-1.#c.e.a.#c1.e1.a1)[M],(A-2.A-1.#c.e.a.#c1.e1.a1)[M],(A-2.A-1.#c.e.a.#c1.e1.a1)[M],(A-2.A-1.#c.e.a.#c1.e1.a1)[M],(A-2.A-1.#c.e.a.#c1.e1.a1)[M],(A-2.A-1.#c.e.a.#c1.e1.a1)[M],(A-2.A-1.#c.e.a.#c1.e1.a1)[M],(A-2.A-1.#c.e.a.#c1.e1.a1)[M],(A-2.A-1.#c.e.a.#c1.e1.a1)[M],(A-2.A-1.#c.e.a.#c1.e1.a1)[M],(A-2.A-1.#c.e.a.#c1.e1.a1)[M],(A-2.A-1.#c.e.a.#c1.e1.a1)[M],(A-2.A-1.#c.e.a.#c1.e1.a1)[M],(A-2.A-1.#c.e.a.#c1.e1.a1)[M],(A-2.A-1.#c.e.a.#c1.e1.a1)[M],(A-2.A-1.#c.e.a.#c1.e1.a1)[M],(A-2.A-1.#c.e.a.#c1.e1.a1)[M],(A-2.A-1.#c.e.a.#c1.e1.a1)[M],(A-2.A-1.#c.e.a.#c1.e1.a1)[M],(A-2.A-1.#c.e.a.#c1.e1.a1)[M],(A-2.A-1.#c.e.a.#c1.e1.a1)[M],(A-2.A-1.#c.e.a.#c1.e1.a1)[M],(A-2.A-1.#c.e.a.#c1.e1.a1)[M],(A-2.A-1.#c.e.a.#c1.e1.a1)[M],(A-2.A-1.#c.e.a.#c1.e1.a1)[M],(A-2.A-1.#c.e.a.#c1.e1.a1)[M],(A-2.A-1.#c.e.a.#c1.e1.a1)[M],(A-2.A-1.#c.e.a.#c1.e1.a1)[M],(A-2.A-1.#c.e.a.#c1.e1.a1)[M],(A-2.A-1.#c.e.a.#c1.e1.a1)[M],(A-2.A-1.#c.e.a.#c1.e1.a1)[M],(A-2.A-1.#c.e.a.#c1.e1.a1)[M],(A-2.A-1.#c.e.a.#c1.e1.a1)[M],(A-2.A-1.#c.e.a.#c1.e1.a1)[M],(A-2.A-1.#c.e.a.#c1.e1.a1)[M],(A-2.A-1.#c.e.a.#c1.e1.a1)[M],(A-2.A-1.#c.e.a.#c1.e1.a1)[M],(A-2.A-1.#c.e.a.#c1.e1.a1)[M],(A-2.A-1.#c.e.a.#c1.e1.a1)[M],(A-2.A-1.#c.e.a.#c1.e1.a1)[M],(A-2.A-1.#c.e.a.#c1.e1.a1)[M],(A-2.A-1.#c.e.a.#c1.e1.a1)[M],(A-2.A-1.#c.e.a.#c1.e1.a1)[M],(A-2.A-1.#c.e.a.#c1.e1.a1)[M],(A-2.A-1.#c.e.a.#c1.e1.a1)[M],(A-2.A-1.#c.e.a.#c1.e1.a1)[M],(A-2.A-1.#c.e.a.#c1.e1.a1)[M],(A-2.A-1.#c.e.a.#c1.e1.a1)[M],(A-2.A-1.#c.e.a.#c1.e1.a1)[M],(A-2.A-1.#c.e.a.#c1.e1.a1)[M],(A-2.A-1.#c.e.a.#c1.e1.a1)[M],(A-2.A-1.#c.e.a.#c1.e1.a1)[M],(A-2.A-1.#c.e.a.#c1.e1.a1)[M],(A-2.A-1.#c.e.a.#c1.e1.a1)[M],(A-2.A-1.#c.e.a.#c1.e1.a1)[M],(A-2.A-1.#c.e.a.#c1.e1.a1)[M],(A-2.A-1.#c.e.a.#c1.e1.a1)[M],(A-2.A-1.#c.e.a.#c1.e1.a1)[M],(A-2.A-1.#c.e.a.#c1.e1.a1)[M],(A-2.A-1.#c.e.a.#c1.e1.a1)[M],(A-2.A-1.#c.e.a.#c1.e1.a1)[M],(A-2.A-1.#c.e.a.#c1.e1.a1)[M],(A-2.A-1.#c.e.a.#c1.e1.a1)[M],(A-2.A-1.#c.e.a.#c1.e1.a1)[M],(A-2.A-1.#c.e.a.#c1.e1.a1)[M],(A-2.A-1.#c.e.a.#c1.e1.a1)[M],(A-2.A-1.#c.e.a.#c1.e1.a1)[M],(A-2.A-1.#c.e.a.#c1.e1.a1)[M],(A-2.A-1.#c.e.a.#c1.e1.a1)[M],(A-2.A-1.#c.e.a.#c1.e1.a1)[M],(A-2.A-1.#c.e.a.#c1.e1.a1)[M],(A-2.A-1.#c.e.a.#c1.e1.a1)[M],(A-2.A-1.#c.e.a.#c1.e1.a1)[M],(A-2.A-1.#c.e.a.#c1.e1.a1)[M],(A-2.A-1.#c.e.a.#c1.e1.a1)[M],(A-2.A-1.#c.e.a.#c1.e1.a1)[M],(A-2.A-1.#c.e.a.#c1.e1.a1)[M],(A-2.A-1.#c.e.a.#c1.e1.a1)[M],(A-2.A-1.#c.e.a.#c1.e1.a1)[M],(A-2.A-1.#c.e.a.#c1.e1.a1)[M],(A-2.A-1.#c.e.a.#c1.e1.a1)[M],(A-2.A-1.#c.e.a.#c1.e1.a1)[M],(A-2.A-1.#c.e.a.#c1.e1.a1)[M],(A-2.A-1.#c.e.a.#c1.e1.a1)[M],(A-2.A-1.#c.e.a.#c1.e1.a1)[M],(A-2.A-1.#c.e.a.#c1.e1.a1)[M],(A-2.A-1.#c.e.a.#c1.e1.a1)[M],(A-2.A-1.#c.e.a.#c1.e1.a1)[M],(A-2.A-1.#c.e.a.#c1.e1.a1)[M],(A-2.A-1.#c.e.a.#c1.e1.a1)[M],(A-2.A-1.#c.e.a.#c1.e1.a1)[M],(A-2.A-1.#c.e.a.#c1.e1.a1)[M],(A-2.A-1.#c.e.a.#c1.e1.a1)[M],(A-2.A-1.#c.e.a.#c1.e1.a1)[M],(A-2.A-1.#c.e.a.#c1.e1.a1)[M],(A-2.A-1.#c.e.a.#c1.e1.a1)[M],(A-2.A-1.#c.e.a.#c1.e1.a1)[M],(A-2.A-1.#c.e.a.#c1.e1.a1)[M],(A-2.A-1.#c.e.a.#c1.e1.a1)[M],(A-2.A-1.#c.e.a.#c1.e1.a1)[M],(A-2.A-1.#c.e.a.#c1.e1.a1)[M],(A-2.A-1.#c.e.a.#c1.e1.a1)[M],(A-2.A-1.#c.e.a.#c1.e1.a1)[M],(A-2.A-1.#c.e.a.#c1.e1.a1)[M],(A-2.A-1.#c.e.a.#c1.e1.a1)[M],(A-2.A-1.#c.e.a.#c1.e1.a1)[M],(A-2.A-1.#c.e.a.#c1.e1.a1)[M],(A-2.A-1.#c.e.a.#c1.e1.a1)[M],(A-2.A-1.#c.e.a.#c1.e1.a1)[M],(A-2.A-1.#c.e.a.#c1.e1.a1)[M],(A-2.A-1.#c.e.a.#c1.e1.a1)[M],(A-2.A-1.#c.e.a.#c1.e1.a1)[M],(A-2.A-1.#c.e.a.#c1.e1.a1)[M],(A-2.A-1.#c.e.a.#c1.e1.a1)[M],(A-2.A-1.#c.e.a.#c1.e1.a1)[M],(A-2.A-1.#c.e.a.#c1.e1.a1)[M],(A-2.A-1.#c.e.a.#c1.e1.a1)[M],(A-2.A-1.#c.e.a.#c1.e1.a1)[M],(A-2.A-1.#c.e.a.#c1.e1.a1)[M],(A-2.A-1.#c.e.a.#c1.e1.a1)[M],(A-2.A-1.#c.e.a.#c1.e1.a1)[M],(A-2.A-1.#c.e.a.#c1.e1.a1)[M],(A-2.A-1.#c.e.a.#c1.e1.a1)[M],(A-2.A-1.#c.e.a.#c1.e1.a1)[M],(A-2.A-1.#c.e.a.#c1.e1.a1)[M],(A-2.A-1.#c.e.a.#c1.e1.a1)[M],(A-2.A-1.#c.e.a.#c1.e1.a1)[M],(A-2.A-1.#c.e.a.#c1.e1.a1)[M],(A-2.A-1.#c.e.a.#c1.e1.a1)[M],(A-2.A-1.#c.e.a.#c1.e1.a1)[M],(A-2.A-1.#c.e.a.#c1.e1.a1)[M],(A-2.A-1.#c.e.a.#c1.e1.a1)[M],(A-2.A-1.#c.e.a.#c1.e1.a1)[M],(A-2.A-1.#c.e.a.#c1.e1.a1)[M],(A-2.A-1.#c.e.a.#c1.e1.a1)[M],(A-2.A-1.#c.e.a.#c1.e1.a1)[M],(A-2.A-1.#c.e.a.#c1.e1.a1)[M],(A-2.A-1.#c.e.a.#c1.e1.a1)[M],(A-2.A-1.#c.e.a.#c1.e1.a1)[M],(A-2.A-1.#c.e.a.#c1.e1.a1)[M],(A-2.A-1.#c.e.a.#c1.e1.a1)[M],(A-2.A-1.#c.e.a.#c1.e1.a1)[M],(A-2.A-1.#c.e.a.#c1.e1.a1)[M],(A-2.A-1.#c.e.a.#c1.e1.a1)[M],(A-2.A-1.#c.e.a.#c1.e1.a1)[M],(A-2.A-1.#c.e.a.#c1.e1.a1)[M],(A-2.A-1.#c.e.a.#c1.e1.a1)[M],(A-2.A-1.#c.e.a.#c1.e1.a1)[M],(A-2.A-1.#c.e.a.#c1.e1.a1)[M],(A-2.A-1.#c.e.a.#c1.e1.a1)[M],(A-2.A-1.#c.e.a.#c1.e1.a1)[M],(A-2.A-1.#c.e.a.#c1.e1.a1)[M],(A-2.A-1.#c.e.a.#c1.e1.a1)[M],(A-2.A-1.#c.e.a.#c1.e1.a1)[M],(A-2.A-1.#c.e.a.#c1.e1.a1)[M],(A-2.A-1.#c.e.a.#c1.e1.a1)[M],(A-2.A-1.#c.e.a.#c1.e1.a1)[M],(A-2.A-1.#c.e.a.#c1.e1.a1)[M],(A-2.A-1.#c.e.a.#c1.e1.a1)[M],(A-2.A-1.#c.e.a.#c1.e1.a1)[M],(A-2.A-1.#c.e.a.#c1.e1.a1)[M],(A-2.A-1.#c.e.a.#c1.e1.a1)[M],(A-2.A-1.#c.e.a.#c1.e1.a1)[M],(A-2.A-1.#c.e.a.#c1.e1.a1)[M],(A-2.A-1.#c.e.a.#c1.e1.a1)[M],(A-2.A-1.#c.e.a.#c1.e1.a1)[M],(A-2.A-1.#c.e.a.#c1.e1.a1)[M],(A-2.A-1.#c.e.a.#c1.e1.a1)[M],(A-2.A-1.#c.e.a.#c1.e1.a1)[M],(A-2.A-1.#c.e.a.#c1.e1.a1)[M],(A-2.A-1.#c.e.a.#c1.e1.a1)[M],(A-2.A-1.#c.e.a.#c1.e1.a1)[M],(A-2.A-1.#c.e.a.#c1.e1.a1)[M],(A-2.A-1.#c.e.a.#c1.e1.a1)[M],(A-2.A-1.#c.e.a.#c1.e1.a1)[M],(A-2.A-1.#c.e.a.#c1.e1.a1)[M],(A-2.A-1.#c.e.a.#c1.e1.a1)[M],(A-2.A-1.#c.e.a.#c1.e1.a1)[M],(A-2.A-1.#c.e.a.#c1.e1.a1)[M],(A-2.A-1.#c.e.a.#c1.e1.a1)[M],(A-2.A-1.#c.e.a.#c1.e1.a1)[M],(A-2.A-1.#c.e.a.#c1.e1.a1)[M],(A-2.A-1.#c.e.a.#c1.e1.a1)[M],(A-2.A-1.#c.e.a.#c1.e1.a1)[M],(A-2.A-1.#c.e.a.#c1.e1.a1)[M],(A-2.A-1.#c.e.a.#c1.e1.a1)[M],(A-2.A-1.#c.e.a.#c1.e1.a1)[M],(A-2.A-1.#c.e.a.#c1.e1.a1)[M],(A-2.A-1.#c.e.a.#c1.e1.a1)[M],(A-2.A-1.#c.e.a.#c1.e1.a1)[M],(A-2.A-1.#c.e.a.#c1.e1.a1)[M],(A-2.A-1.#c.e.a.#c1.e1.a1)[M],(A-2.A-1.#c.e.a.#c1.e1.a1)[M],(A-2.A-1.#c.e.a.#c1.e1.a1)[M],(A-2.A-1.#c.e.a.#c1.e1.a1)[M],(A-2.A-1.#c.e.a.#c1.e1.a1)[M],(A-2.A-1.#c.e.a.#c1.e1.a1)[M],(A-2.A-1.#c.e.a.#c1.e1.a1)[M],(A-2.A-1.#c.e.a.#c1.e1.a1)[M],(A-2.A-1.#c.e.a.#c1.e1.a1)[M],(A-2.A-1.#c.e.a.#c1.e1.a1)[M],(A-2.A-1.#c.e.a.#c1.e1.a1)[M],(A-2.A-1.#c.e.a.#c1.e1.a1)[M],(A-2.A-1.#c.e.a.#c1.e1.a1)[M],(A-2.A-1.#c.e.a.#c1.e1.a1)[M],(A-2.A-1.#c.e.a.#c1.e1.a1)[M],(A-2.A-1.#c.e.a.#c1.e1.a1)[M],(A-2.A-1.#c.e.a.#c1.e1.a1)[M],(A-2.A-1.#c.e.a.#c1.e1.a1)[M],(A-2.A-1.#c.e.a.#c1.e1.a1)[M],(A-2.A-1.#c.e.a.#c1.e1.a1)[M],(A-2.A-1.#c.e.a.#c1.e1.a1)[M],(A-2.A-1.#c.e.a.#c1.e1.a1)[M],(A-2.A-1.#c.e.a.#c1.e1.a1)[M],(A-2.A-1.#c.e.a.#c1.e1.a1)[M],(A-2.A-1.#c.e.a.#c1.e1.a1)[M],(A-2.A-1.#c.e.a.#c1.e1.a1)[M],(A-2.A-1.#c.e.a.#c1.e1.a1)[M],(A-2.A-1.#c.e.a.#c1.e1.a1)[M],(A-2.A-1.#c.e.a.#c1.e1.a1)[M],(A-2.A-1.#c.e.a.#c1.e1.a1)[M],(A-2.A-1.#c.e.a.#c1.e1.a1)[M],(A-2.A-1.#c.e.a.#c1.e1.a1)[M],(A-2.A-1.#c.e.a.#c1.e1.a1)[M],(A-2.A-1.#c.e.a.#c1.e1.a1)[M],(A-2.A-1.#c.e.a.#c1.e1.a1)[M],(A-2.A-1.#c.e.a.#c1.e1.a1)[M],(A-2.A-1.#c.e.a.#c1.e1.a1)[M],(A-2.A-1.#c.e.a.#c1.e1.a1)[M],(A-2.A-1.#c.e.a.#c1.e1.a1)[M],(A-2.A-1.#c.e.a.#c1.e1.a1)[M],(A-2.A-1.#c.e.a.#c1.e1.a1)[M],(A-2.A-1.#c.e.a.#c1.e1.a1)[M],(A-2.A-1.#c.e.a.#c1.e1.a1)[M],(A-2.A-1.#c.e.a.#c1.e1.a1)[M],(A-2.A-1.#c.e.a.#c1.e1.a1)[M],(A-2.A-1.#c.e.a.#c1.e1.a1)[M],(A-2.A-1.#c.e.a.#c1.e1.a1)[M],(A-2.A-1.#c.e.a.#c1.e1.a1)[M],(A-2.A-1.#c.e.a.#c1.e1.a1)[M],(A-2.A-1.#c.e.a.#c1.e1.a1)[M],(A-2.A-1.#c.e.a.#c1.e1.a1)[M],(A-2.A-1.#c.e.a.#c1.e1.a1)[M],(A-2.A-1.#c.e.a.#c1.e1.a1)[M],(A-2.A-1.#c.e.a.#c1.e1.a1)[M],(A-2.A-1.#c.e.a.#c1.e1.a1)[M],(A-2.A-1.#c.e.a.#c1.e1.a1)[M],(A-2.A-1.#c.e.a.#c1.e1.a1)[M],(A-2.A-1.#c.e.a.#c1.e1.a1)[M],(A-2.A-1.#c.e.a.#c1.e1.a1)[M],(A-2.A-1.#c.e.a.#c1.e1.a1)[M],(A-2.A-1.#c.e.a.#c1.e1.a1)[M],(A-2.A-1.#c.e.a.#c1.e1.a1)[M],(A-2.A-1.#c.e.a.#c1.e1.a1)[M],(A-2.A-1.#c.e.a.#c1.e1.a1)[M],(A-2.A-1.#c.e.a.#c1.e1.a1)[M],(A-2.A-1.#c.e.a.#c1.e1.a1)[M],(A-2.A-1.#c.e.a.#c1.e1.a1)[M],(A-2.A-1.#c.e.a.#c1.e1.a1)[M],(A-2.A-1.#c.e.a.#c1.e1.a1)[M],(A-2.A-1.#c.e.a.#c1.e1.a1)[M],(A-2.A-1.#c.e.a.#c1.e1.a1)[M],(A-2.A-1.#c.e.a.#c1.e1.a1)[M],(A-2.A-1.#c.e.a.#c1.e1.a1)[M],(A-2.A-1.#c.e.a.#c1.e1.a1)[M],(A-2.A-1.#c.e.a.#c1.e1.a1)[M],(A-2.A-1.#c.e.a.#c1.e1.a1)[M],(A-2.A-1.#c.e.a.#c1.e1.a1)[M],(A-2.A-1.#c.e.a.#c1.e1.a1)[M],(A-2.A-1.#c.e.a.#c1.e1.a1)[M],(A-2.A-1.#c.e.a.#c1.e1.a1)[M],(A-2.A-1.#c.e.a.#c1.e1.a1)[M],(A-2.A-1.#c.e.a.#c1.e1.a1)[M],(A-2.A-1.#c.e.a.#c1.e1.a1)[M],(A-2.A-1.#c.e.a.#c1.e1.a1)[M],(A-2.A-1.#c.e.a.#c1.e1.a1)[M],(A-2.A-1.#c.e.a.#c1.e1.a1)[M],(A-2.A-1.#c.e.a.#c1.e1.a1)[M],(A-2.A-1.#c.e.a.#c1.e1.a1)[M],(A-2.A-1.#c.e.a.#c1.e1.a1)[M],(A-2.A-1.#c.e.a.#c1.e1.a1)[M],(A-2.A-1.#c.e.a.#c1.e1.a1)[M],(A-2.A-1.#c.e.a.#c1.e1.a1)[M],(A-2.A-1.#c.e.a.#c1.e1.a1)[M],(A-2.A-1.#c.e.a.#c1.e1.a1)[M],(A-2.A-1.#c.e.a.#c1.e1.a1)[M],(A-2.A-1.#c.e.a.#c1.e1.a1)[M],(A-2.A-1.#c.e.a.#c1.e1.a1)[M],(A-2.A-1.#c.e.a.#c1.e1.a1)[M],(A-2.A-1.#c.e.a.#c1.e1.a1)[M],(A-2.A-1.#c.e.a.#c1.e1.a1)[M],(A-2.A-1.#c.e.a.#c1.e1.a1)[M],(A-2.A-1.#c.e.a.#c1.e1.a1)[M],(A-2.A-1.#c.e.a.#c1.e1.a1)[M],(A-2.A-1.#c.e.a.#c1.e1.a1)[M],(A-2.A-1.#c.e.a.#c1.e1.a1)[M],(A-2.A-1.#c.e.a.#c1.e1.a1)[M],(A-2.A-1.#c.e.a.#c1.e1.a1)[M],(A-2.A-1.#c.e.a.#c1.e1.a1)[M],(A-2.A-1.#c.e.a.#c1.e1.a1)[M],(A-2.A-1.#c.e.a.#c1.e1.a1)[M],(A-2.A-1.#c.e.a.#c1.e1.a1)[M],(A-2.A-1.#c.e.a.#c1.e1.a1)[M],(A-2.A-1.#c.e.a.#c1.e1.a1)[M],(A-2.A-1.#c.e.a.#c1.e1.a1)[M],(A-2.A-1.#c.e.a.#c1.e1.a1)[M],(A-2.A-1.#c.e.a.#c1.e1.a1)[M],(A-2.A-1.#c.e.a.#c1.e1.a1)[M],(A-2.A-1.#c.e.a.#c1.e1.a1)[M],(A-2.A-1.#c.e.a.#c1.e1.a1)[M],(A-2.A-1.#c.e.a.#c1.e1.a1)[M],(A-2.A-1.#c.e.a.#c1.e1.a1)[M],(A-2.A-1.#c.e.a.#c1.e1.a1)[M],(A-2.A-1.#c.e.a.#c1.e1.a1)[M],(A-2.A-1.#c.e.a.#c1.e1.a1)[M],(A-2.A-1.#c.e.a.#c1.e1.a1)[M],(A-2.A-1.#c.e.a.#c1.e1.a1)[M],(A-2.A-1.#c.e.a.#c1.e1.a1)[M],(A-2.A-1.#c.e.a.#c1.e1.a1)[M],(A-2.A-1.#c.e.a.#c1.e1.a1)[M],(A-2.A-1.#c.e.a.#c1.e1.a1)[M],(A-2.A-1.#c.e.a.#c1.e1.a1)[M],(A-2.A-1.#c.e.a.#c1.e1.a1)[M],(A-2.A-1.#c.e.a.#c1.e1.a1)[M],(A-2.A-1.#c.e.a.#c1.e1.a1)[M],(A-2.A-1.#c.e.a.#c1.e1.a1)[M],(A-2.A-1.#c.e.a.#c1.e1.a1)[M],(A-2.A-1.#c.e.a.#c1.e1.a1)[M],(A-2.A-1.#c.e.a.#c1.e1.a1)[M],(A-2.A-1.#c.e.a.#c1.e1.a1)[M],(A-2.A-1.#c.e.a.#c1.e1.a1)[M],(A-2.A-1.#c.e.a.#c1.e1.a1)[M],(A-2.A-1.#c.e.a.#c1.e1.a1)[M],(A-2.A-1.#c.e.a.#c1.e1.a1)[M],(A-2.A-1.#c.e.a.#c1.e1.a1)[M],(A-2.A-1.#c.e.a.#c1.e1.a1)[M],(A-2.A-1.#c.e.a.#c1.e1.a1)[M],(A-2.A-1.#c.e.a.#c1.e1.a1)[M],(A-2.A-1.#c.e.a.#c1.e1.a1)[M],(A-2.A-1.#c.e.a.#c1.e1.a1)[M]>,(C-2.E-2.G-2.C-1.E-1.G-1.c.e.g.c1.e1.g1.c2.e2.g2.c3.e3.g3.c4.e4.g4.c5)[HHHHHHHH];"]}]}
